{"id":40831964,"title":"The super effectiveness of Pokémon embeddings using only raw JSON and images","url":"https://minimaxir.com/2024/06/pokemon-embeddings/","score":169,"comments_count":28,"submitted_at":"2024-06-29T17:03:53.000Z","scorestamps":[{"score":1,"tracked_at":"2024-06-29T17:04:31.243Z"},{"score":2,"tracked_at":"2024-06-30T00:47:38.674Z"},{"score":7,"tracked_at":"2024-06-30T17:35:29.823Z"},{"score":6,"tracked_at":"2024-06-30T17:30:04.991Z"},{"score":9,"tracked_at":"2024-06-30T17:41:54.595Z"},{"score":46,"tracked_at":"2024-06-30T19:52:22.611Z"},{"score":10,"tracked_at":"2024-06-30T17:43:33.532Z"},{"score":14,"tracked_at":"2024-06-30T17:57:27.834Z"},{"score":25,"tracked_at":"2024-06-30T18:47:13.805Z"},{"score":3,"tracked_at":"2024-06-30T17:10:31.689Z"},{"score":16,"tracked_at":"2024-06-30T18:02:53.334Z"},{"score":17,"tracked_at":"2024-06-30T18:10:24.961Z"},{"score":12,"tracked_at":"2024-06-30T17:48:20.919Z"},{"score":21,"tracked_at":"2024-06-30T18:17:25.481Z"},{"score":8,"tracked_at":"2024-06-30T17:37:05.429Z"},{"score":24,"tracked_at":"2024-06-30T18:42:55.359Z"},{"score":37,"tracked_at":"2024-06-30T19:16:54.972Z"},{"score":20,"tracked_at":"2024-06-30T18:14:10.484Z"},{"score":4,"tracked_at":"2024-06-30T17:19:46.446Z"},{"score":5,"tracked_at":"2024-06-30T17:22:26.530Z"},{"score":11,"tracked_at":"2024-06-30T17:45:41.714Z"},{"score":13,"tracked_at":"2024-06-30T17:52:02.830Z"},{"score":15,"tracked_at":"2024-06-30T17:59:09.485Z"},{"score":23,"tracked_at":"2024-06-30T18:27:11.525Z"},{"score":35,"tracked_at":"2024-06-30T19:11:59.299Z"},{"score":22,"tracked_at":"2024-06-30T18:20:08.479Z"},{"score":27,"tracked_at":"2024-06-30T18:51:37.622Z"},{"score":31,"tracked_at":"2024-06-30T18:58:40.983Z"},{"score":52,"tracked_at":"2024-06-30T20:07:44.129Z"},{"score":53,"tracked_at":"2024-06-30T20:10:29.430Z"},{"score":26,"tracked_at":"2024-06-30T18:47:48.794Z"},{"score":38,"tracked_at":"2024-06-30T19:17:25.570Z"},{"score":43,"tracked_at":"2024-06-30T19:42:01.311Z"},{"score":40,"tracked_at":"2024-06-30T19:39:17.477Z"},{"score":28,"tracked_at":"2024-06-30T18:55:23.732Z"},{"score":32,"tracked_at":"2024-06-30T19:00:53.690Z"},{"score":33,"tracked_at":"2024-06-30T19:07:20.417Z"},{"score":34,"tracked_at":"2024-06-30T19:11:28.510Z"},{"score":29,"tracked_at":"2024-06-30T18:56:29.238Z"},{"score":36,"tracked_at":"2024-06-30T19:13:38.008Z"},{"score":39,"tracked_at":"2024-06-30T19:21:11.227Z"},{"score":47,"tracked_at":"2024-06-30T19:55:05.187Z"},{"score":48,"tracked_at":"2024-06-30T19:57:49.394Z"},{"score":59,"tracked_at":"2024-06-30T20:45:10.871Z"},{"score":66,"tracked_at":"2024-06-30T21:06:32.947Z"},{"score":64,"tracked_at":"2024-06-30T20:58:58.558Z"},{"score":55,"tracked_at":"2024-06-30T20:21:29.146Z"},{"score":51,"tracked_at":"2024-06-30T20:06:38.588Z"},{"score":41,"tracked_at":"2024-06-30T19:39:49.899Z"},{"score":54,"tracked_at":"2024-06-30T20:16:02.921Z"},{"score":42,"tracked_at":"2024-06-30T19:41:28.477Z"},{"score":44,"tracked_at":"2024-06-30T19:43:42.933Z"},{"score":50,"tracked_at":"2024-06-30T19:59:58.803Z"},{"score":75,"tracked_at":"2024-06-30T21:40:33.555Z"},{"score":71,"tracked_at":"2024-06-30T21:18:58.499Z"},{"score":56,"tracked_at":"2024-06-30T20:33:16.770Z"},{"score":57,"tracked_at":"2024-06-30T20:39:45.800Z"},{"score":60,"tracked_at":"2024-06-30T20:48:20.180Z"},{"score":58,"tracked_at":"2024-06-30T20:41:21.083Z"},{"score":61,"tracked_at":"2024-06-30T20:51:33.622Z"},{"score":65,"tracked_at":"2024-06-30T21:04:57.221Z"},{"score":68,"tracked_at":"2024-06-30T21:10:20.311Z"},{"score":77,"tracked_at":"2024-06-30T21:52:17.124Z"},{"score":62,"tracked_at":"2024-06-30T20:53:42.204Z"},{"score":63,"tracked_at":"2024-06-30T20:57:23.676Z"},{"score":67,"tracked_at":"2024-06-30T21:07:04.048Z"},{"score":69,"tracked_at":"2024-06-30T21:16:51.356Z"},{"score":74,"tracked_at":"2024-06-30T21:38:23.766Z"},{"score":72,"tracked_at":"2024-06-30T21:20:03.777Z"},{"score":79,"tracked_at":"2024-06-30T22:02:27.029Z"},{"score":76,"tracked_at":"2024-06-30T21:44:47.467Z"},{"score":73,"tracked_at":"2024-06-30T21:34:36.578Z"},{"score":78,"tracked_at":"2024-06-30T22:00:21.817Z"},{"score":80,"tracked_at":"2024-06-30T22:04:37.629Z"},{"score":95,"tracked_at":"2024-06-30T23:22:06.882Z"},{"score":90,"tracked_at":"2024-06-30T22:57:37.457Z"},{"score":83,"tracked_at":"2024-06-30T22:23:45.882Z"},{"score":81,"tracked_at":"2024-06-30T22:12:06.095Z"},{"score":89,"tracked_at":"2024-06-30T22:43:05.870Z"},{"score":105,"tracked_at":"2024-07-01T00:22:13.696Z"},{"score":82,"tracked_at":"2024-06-30T22:14:13.229Z"},{"score":86,"tracked_at":"2024-06-30T22:33:52.042Z"},{"score":84,"tracked_at":"2024-06-30T22:24:18.922Z"},{"score":85,"tracked_at":"2024-06-30T22:29:34.397Z"},{"score":87,"tracked_at":"2024-06-30T22:36:01.974Z"},{"score":88,"tracked_at":"2024-06-30T22:37:06.919Z"},{"score":103,"tracked_at":"2024-07-01T00:07:56.650Z"},{"score":91,"tracked_at":"2024-06-30T22:59:12.300Z"},{"score":97,"tracked_at":"2024-06-30T23:29:03.723Z"},{"score":102,"tracked_at":"2024-07-01T00:02:05.131Z"},{"score":92,"tracked_at":"2024-06-30T23:03:01.948Z"},{"score":94,"tracked_at":"2024-06-30T23:17:20.996Z"},{"score":96,"tracked_at":"2024-06-30T23:27:25.615Z"},{"score":101,"tracked_at":"2024-07-01T00:01:00.986Z"},{"score":98,"tracked_at":"2024-06-30T23:53:32.028Z"},{"score":100,"tracked_at":"2024-07-01T00:00:32.011Z"},{"score":99,"tracked_at":"2024-06-30T23:56:10.634Z"},{"score":104,"tracked_at":"2024-07-01T00:15:53.119Z"},{"score":106,"tracked_at":"2024-07-01T00:27:30.475Z"},{"score":108,"tracked_at":"2024-07-01T00:43:54.572Z"},{"score":112,"tracked_at":"2024-07-01T01:14:02.800Z"},{"score":111,"tracked_at":"2024-07-01T00:58:11.149Z"},{"score":114,"tracked_at":"2024-07-01T01:33:10.515Z"},{"score":110,"tracked_at":"2024-07-01T00:52:21.580Z"},{"score":118,"tracked_at":"2024-07-01T02:34:41.641Z"},{"score":113,"tracked_at":"2024-07-01T01:25:43.940Z"},{"score":115,"tracked_at":"2024-07-01T01:40:08.264Z"},{"score":121,"tracked_at":"2024-07-01T02:38:55.814Z"},{"score":116,"tracked_at":"2024-07-01T02:13:05.663Z"},{"score":117,"tracked_at":"2024-07-01T02:25:46.237Z"},{"score":119,"tracked_at":"2024-07-01T02:35:13.880Z"},{"score":120,"tracked_at":"2024-07-01T02:37:51.893Z"},{"score":123,"tracked_at":"2024-07-01T02:53:42.617Z"},{"score":125,"tracked_at":"2024-07-01T03:15:18.121Z"},{"score":124,"tracked_at":"2024-07-01T03:08:24.547Z"},{"score":132,"tracked_at":"2024-07-01T05:41:12.245Z"},{"score":126,"tracked_at":"2024-07-01T03:34:33.812Z"},{"score":128,"tracked_at":"2024-07-01T04:32:51.335Z"},{"score":130,"tracked_at":"2024-07-01T05:10:48.652Z"},{"score":131,"tracked_at":"2024-07-01T05:29:54.528Z"},{"score":127,"tracked_at":"2024-07-01T04:22:45.820Z"},{"score":129,"tracked_at":"2024-07-01T05:01:46.976Z"},{"score":133,"tracked_at":"2024-07-01T05:43:19.758Z"},{"score":134,"tracked_at":"2024-07-01T06:05:10.672Z"},{"score":143,"tracked_at":"2024-07-01T07:37:54.081Z"},{"score":135,"tracked_at":"2024-07-01T06:06:46.581Z"},{"score":136,"tracked_at":"2024-07-01T06:10:28.103Z"},{"score":140,"tracked_at":"2024-07-01T07:18:47.775Z"},{"score":137,"tracked_at":"2024-07-01T06:28:04.755Z"},{"score":138,"tracked_at":"2024-07-01T06:52:55.158Z"},{"score":139,"tracked_at":"2024-07-01T07:12:31.604Z"},{"score":145,"tracked_at":"2024-07-01T08:10:59.267Z"},{"score":141,"tracked_at":"2024-07-01T07:22:30.485Z"},{"score":142,"tracked_at":"2024-07-01T07:37:20.675Z"},{"score":144,"tracked_at":"2024-07-01T07:54:22.286Z"},{"score":150,"tracked_at":"2024-07-01T09:00:30.237Z"},{"score":146,"tracked_at":"2024-07-01T08:46:30.430Z"},{"score":147,"tracked_at":"2024-07-01T08:55:36.303Z"},{"score":148,"tracked_at":"2024-07-01T08:57:43.314Z"},{"score":149,"tracked_at":"2024-07-01T08:58:47.290Z"},{"score":151,"tracked_at":"2024-07-01T12:47:27.596Z"},{"score":152,"tracked_at":"2024-07-01T15:41:56.193Z"},{"score":153,"tracked_at":"2024-07-01T17:21:14.806Z"},{"score":154,"tracked_at":"2024-07-01T17:41:10.467Z"},{"score":155,"tracked_at":"2024-07-01T17:43:25.175Z"},{"score":156,"tracked_at":"2024-07-01T18:04:42.357Z"},{"score":157,"tracked_at":"2024-07-01T20:26:45.120Z"},{"score":159,"tracked_at":"2024-07-01T21:06:28.512Z"},{"score":158,"tracked_at":"2024-07-01T20:57:34.637Z"},{"score":160,"tracked_at":"2024-07-01T22:41:32.703Z"},{"score":161,"tracked_at":"2024-07-01T23:47:28.496Z"},{"score":162,"tracked_at":"2024-07-02T07:24:38.832Z"},{"score":163,"tracked_at":"2024-07-02T13:18:00.874Z"},{"score":164,"tracked_at":"2024-07-02T16:44:45.461Z"},{"score":165,"tracked_at":"2024-07-03T03:29:09.755Z"},{"score":166,"tracked_at":"2024-07-03T12:12:48.120Z"},{"score":167,"tracked_at":"2024-07-03T13:40:41.013Z"},{"score":168,"tracked_at":"2024-07-04T01:55:42.435Z"},{"score":169,"tracked_at":"2024-07-04T07:08:51.315Z"}],"descendants_count_stamps":[{"count":17,"tracked_at":"2024-07-01T02:45:18.218Z"},{"count":18,"tracked_at":"2024-07-01T02:55:18.924Z"},{"count":5,"tracked_at":"2024-06-30T19:07:54.918Z"},{"count":6,"tracked_at":"2024-06-30T19:19:03.251Z"},{"count":9,"tracked_at":"2024-06-30T20:06:38.680Z"},{"count":10,"tracked_at":"2024-06-30T20:53:08.227Z"},{"count":11,"tracked_at":"2024-06-30T21:49:36.678Z"},{"count":19,"tracked_at":"2024-07-01T06:39:44.435Z"},{"count":13,"tracked_at":"2024-06-30T22:17:23.247Z"},{"count":20,"tracked_at":"2024-07-01T07:12:31.687Z"},{"count":12,"tracked_at":"2024-06-30T22:03:34.247Z"},{"count":16,"tracked_at":"2024-07-01T01:32:05.421Z"},{"count":14,"tracked_at":"2024-07-01T00:39:10.019Z"},{"count":24,"tracked_at":"2024-07-01T09:08:55.855Z"},{"count":25,"tracked_at":"2024-07-01T09:19:05.451Z"},{"count":0,"tracked_at":"2024-06-29T17:04:31.287Z"},{"count":21,"tracked_at":"2024-07-01T08:50:48.329Z"},{"count":22,"tracked_at":"2024-07-01T08:55:36.411Z"},{"count":23,"tracked_at":"2024-07-01T09:05:11.994Z"},{"count":15,"tracked_at":"2024-07-01T01:20:56.687Z"},{"count":26,"tracked_at":"2024-07-01T14:28:28.014Z"},{"count":28,"tracked_at":"2024-07-02T07:08:04.429Z"},{"count":4,"tracked_at":"2024-06-30T18:30:25.713Z"},{"count":8,"tracked_at":"2024-06-30T19:51:17.915Z"},{"count":1,"tracked_at":"2024-06-30T18:06:05.945Z"},{"count":3,"tracked_at":"2024-06-30T18:26:39.210Z"},{"count":2,"tracked_at":"2024-06-30T18:22:51.238Z"},{"count":7,"tracked_at":"2024-06-30T19:29:24.729Z"},{"count":27,"tracked_at":"2024-07-01T22:57:25.291Z"}],"rankstamps":[{"rank":13,"tracked_at":"2024-06-30T17:11:00.735Z"},{"rank":14,"tracked_at":"2024-06-30T17:16:54.998Z"},{"rank":9,"tracked_at":"2024-06-30T17:19:41.720Z"},{"rank":8,"tracked_at":"2024-06-30T17:30:01.151Z"},{"rank":9,"tracked_at":"2024-06-30T17:40:16.798Z"},{"rank":10,"tracked_at":"2024-06-30T17:44:33.533Z"},{"rank":12,"tracked_at":"2024-06-30T17:46:10.706Z"},{"rank":13,"tracked_at":"2024-06-30T17:48:49.536Z"},{"rank":12,"tracked_at":"2024-06-30T17:51:59.577Z"},{"rank":11,"tracked_at":"2024-06-30T17:57:23.435Z"},{"rank":12,"tracked_at":"2024-06-30T17:58:32.374Z"},{"rank":9,"tracked_at":"2024-06-30T17:59:04.994Z"},{"rank":10,"tracked_at":"2024-06-30T18:10:52.382Z"},{"rank":11,"tracked_at":"2024-06-30T18:27:39.765Z"},{"rank":10,"tracked_at":"2024-06-30T18:32:31.346Z"},{"rank":8,"tracked_at":"2024-06-30T18:35:49.580Z"},{"rank":6,"tracked_at":"2024-06-30T18:42:17.377Z"},{"rank":7,"tracked_at":"2024-06-30T18:50:59.306Z"},{"rank":6,"tracked_at":"2024-06-30T18:51:32.860Z"},{"rank":5,"tracked_at":"2024-06-30T18:54:16.415Z"},{"rank":6,"tracked_at":"2024-06-30T18:55:52.264Z"},{"rank":5,"tracked_at":"2024-06-30T19:00:48.171Z"},{"rank":6,"tracked_at":"2024-06-30T19:06:45.322Z"},{"rank":7,"tracked_at":"2024-06-30T19:07:17.357Z"},{"rank":8,"tracked_at":"2024-06-30T19:08:22.152Z"},{"rank":9,"tracked_at":"2024-06-30T19:10:30.613Z"},{"rank":10,"tracked_at":"2024-06-30T19:11:24.523Z"},{"rank":8,"tracked_at":"2024-06-30T19:11:56.761Z"},{"rank":10,"tracked_at":"2024-06-30T19:12:28.197Z"},{"rank":11,"tracked_at":"2024-06-30T19:15:11.228Z"},{"rank":9,"tracked_at":"2024-06-30T19:16:49.709Z"},{"rank":11,"tracked_at":"2024-06-30T19:24:54.761Z"},{"rank":12,"tracked_at":"2024-06-30T19:26:00.721Z"},{"rank":13,"tracked_at":"2024-06-30T19:27:41.702Z"},{"rank":14,"tracked_at":"2024-06-30T19:34:14.442Z"},{"rank":15,"tracked_at":"2024-06-30T19:38:04.123Z"},{"rank":13,"tracked_at":"2024-06-30T19:39:45.761Z"},{"rank":10,"tracked_at":"2024-06-30T19:43:36.100Z"},{"rank":11,"tracked_at":"2024-06-30T19:44:42.641Z"},{"rank":10,"tracked_at":"2024-06-30T19:45:46.645Z"},{"rank":9,"tracked_at":"2024-06-30T19:46:18.218Z"},{"rank":10,"tracked_at":"2024-06-30T19:50:08.328Z"},{"rank":9,"tracked_at":"2024-06-30T19:50:41.685Z"},{"rank":8,"tracked_at":"2024-06-30T19:52:18.077Z"},{"rank":7,"tracked_at":"2024-06-30T19:57:42.811Z"},{"rank":8,"tracked_at":"2024-06-30T20:14:17.749Z"},{"rank":9,"tracked_at":"2024-06-30T20:38:35.807Z"},{"rank":7,"tracked_at":"2024-06-30T20:39:41.839Z"},{"rank":6,"tracked_at":"2024-06-30T20:42:55.311Z"},{"rank":5,"tracked_at":"2024-06-30T20:46:40.092Z"},{"rank":6,"tracked_at":"2024-06-30T20:48:48.317Z"},{"rank":5,"tracked_at":"2024-06-30T20:50:56.916Z"},{"rank":6,"tracked_at":"2024-06-30T20:59:58.718Z"},{"rank":7,"tracked_at":"2024-06-30T21:02:39.546Z"},{"rank":8,"tracked_at":"2024-06-30T21:04:52.409Z"},{"rank":7,"tracked_at":"2024-06-30T21:07:32.898Z"},{"rank":8,"tracked_at":"2024-06-30T21:11:21.216Z"},{"rank":7,"tracked_at":"2024-06-30T21:26:27.183Z"},{"rank":8,"tracked_at":"2024-06-30T21:28:38.413Z"},{"rank":9,"tracked_at":"2024-06-30T21:35:41.166Z"},{"rank":10,"tracked_at":"2024-06-30T21:40:29.521Z"},{"rank":11,"tracked_at":"2024-06-30T21:43:07.592Z"},{"rank":10,"tracked_at":"2024-06-30T21:52:13.791Z"},{"rank":11,"tracked_at":"2024-06-30T22:04:34.914Z"},{"rank":12,"tracked_at":"2024-06-30T22:31:38.803Z"},{"rank":11,"tracked_at":"2024-06-30T22:42:59.710Z"},{"rank":10,"tracked_at":"2024-06-30T23:05:07.191Z"},{"rank":11,"tracked_at":"2024-06-30T23:08:18.353Z"},{"rank":12,"tracked_at":"2024-06-30T23:21:00.523Z"},{"rank":11,"tracked_at":"2024-06-30T23:22:35.869Z"},{"rank":10,"tracked_at":"2024-06-30T23:31:07.097Z"},{"rank":9,"tracked_at":"2024-06-30T23:32:11.992Z"},{"rank":10,"tracked_at":"2024-07-01T00:08:57.596Z"},{"rank":11,"tracked_at":"2024-07-01T00:30:38.638Z"},{"rank":12,"tracked_at":"2024-07-01T00:40:44.045Z"},{"rank":13,"tracked_at":"2024-07-01T00:45:27.557Z"},{"rank":12,"tracked_at":"2024-07-01T00:58:09.669Z"},{"rank":13,"tracked_at":"2024-07-01T01:02:54.257Z"},{"rank":14,"tracked_at":"2024-07-01T01:11:55.026Z"},{"rank":13,"tracked_at":"2024-07-01T01:19:49.646Z"},{"rank":14,"tracked_at":"2024-07-01T01:27:48.542Z"},{"rank":13,"tracked_at":"2024-07-01T01:33:07.366Z"},{"rank":12,"tracked_at":"2024-07-01T01:40:37.347Z"},{"rank":13,"tracked_at":"2024-07-01T01:41:41.761Z"},{"rank":14,"tracked_at":"2024-07-01T01:44:21.621Z"},{"rank":13,"tracked_at":"2024-07-01T01:44:54.094Z"},{"rank":14,"tracked_at":"2024-07-01T01:49:09.273Z"},{"rank":13,"tracked_at":"2024-07-01T01:51:18.593Z"},{"rank":14,"tracked_at":"2024-07-01T01:53:57.601Z"},{"rank":13,"tracked_at":"2024-07-01T02:05:38.387Z"},{"rank":14,"tracked_at":"2024-07-01T02:27:19.146Z"},{"rank":13,"tracked_at":"2024-07-01T02:33:35.699Z"},{"rank":14,"tracked_at":"2024-07-01T02:34:07.987Z"},{"rank":15,"tracked_at":"2024-07-01T02:43:05.635Z"},{"rank":16,"tracked_at":"2024-07-01T02:48:55.511Z"},{"rank":15,"tracked_at":"2024-07-01T02:49:58.480Z"},{"rank":14,"tracked_at":"2024-07-01T02:54:43.831Z"},{"rank":15,"tracked_at":"2024-07-01T03:00:55.791Z"},{"rank":16,"tracked_at":"2024-07-01T03:03:35.235Z"},{"rank":17,"tracked_at":"2024-07-01T03:17:23.804Z"},{"rank":16,"tracked_at":"2024-07-01T03:18:26.300Z"},{"rank":17,"tracked_at":"2024-07-01T03:18:57.860Z"},{"rank":18,"tracked_at":"2024-07-01T03:19:30.757Z"},{"rank":17,"tracked_at":"2024-07-01T03:28:01.518Z"},{"rank":16,"tracked_at":"2024-07-01T03:29:39.603Z"},{"rank":17,"tracked_at":"2024-07-01T03:32:23.229Z"},{"rank":16,"tracked_at":"2024-07-01T03:49:15.083Z"},{"rank":15,"tracked_at":"2024-07-01T03:50:49.193Z"},{"rank":16,"tracked_at":"2024-07-01T03:55:37.442Z"},{"rank":17,"tracked_at":"2024-07-01T04:21:07.879Z"},{"rank":18,"tracked_at":"2024-07-01T04:37:33.266Z"},{"rank":17,"tracked_at":"2024-07-01T04:43:54.548Z"},{"rank":16,"tracked_at":"2024-07-01T04:53:23.542Z"},{"rank":17,"tracked_at":"2024-07-01T04:57:01.890Z"},{"rank":18,"tracked_at":"2024-07-01T04:57:33.496Z"},{"rank":19,"tracked_at":"2024-07-01T04:58:05.856Z"},{"rank":20,"tracked_at":"2024-07-01T05:04:53.891Z"},{"rank":21,"tracked_at":"2024-07-01T05:12:21.520Z"},{"rank":20,"tracked_at":"2024-07-01T05:30:23.792Z"},{"rank":19,"tracked_at":"2024-07-01T05:34:37.487Z"},{"rank":18,"tracked_at":"2024-07-01T05:38:57.354Z"},{"rank":19,"tracked_at":"2024-07-01T05:43:15.528Z"},{"rank":20,"tracked_at":"2024-07-01T05:51:48.437Z"},{"rank":21,"tracked_at":"2024-07-01T05:54:59.302Z"},{"rank":22,"tracked_at":"2024-07-01T05:59:19.860Z"},{"rank":21,"tracked_at":"2024-07-01T06:02:29.185Z"},{"rank":22,"tracked_at":"2024-07-01T06:06:43.400Z"},{"rank":21,"tracked_at":"2024-07-01T06:08:17.426Z"},{"rank":22,"tracked_at":"2024-07-01T06:08:50.830Z"},{"rank":21,"tracked_at":"2024-07-01T06:09:22.087Z"},{"rank":20,"tracked_at":"2024-07-01T06:11:29.415Z"},{"rank":21,"tracked_at":"2024-07-01T06:25:49.754Z"},{"rank":20,"tracked_at":"2024-07-01T06:42:21.889Z"},{"rank":21,"tracked_at":"2024-07-01T07:06:08.664Z"},{"rank":22,"tracked_at":"2024-07-01T07:08:47.138Z"},{"rank":23,"tracked_at":"2024-07-01T07:21:55.005Z"},{"rank":24,"tracked_at":"2024-07-01T07:25:08.615Z"},{"rank":25,"tracked_at":"2024-07-01T07:27:14.535Z"},{"rank":26,"tracked_at":"2024-07-01T07:28:17.330Z"},{"rank":27,"tracked_at":"2024-07-01T07:30:53.537Z"},{"rank":26,"tracked_at":"2024-07-01T07:31:58.518Z"},{"rank":25,"tracked_at":"2024-07-01T07:34:04.808Z"},{"rank":26,"tracked_at":"2024-07-01T07:42:38.469Z"},{"rank":25,"tracked_at":"2024-07-01T07:55:22.679Z"},{"rank":26,"tracked_at":"2024-07-01T07:56:57.086Z"},{"rank":27,"tracked_at":"2024-07-01T08:00:09.100Z"},{"rank":26,"tracked_at":"2024-07-01T08:02:20.161Z"},{"rank":27,"tracked_at":"2024-07-01T08:08:47.746Z"},{"rank":28,"tracked_at":"2024-07-01T08:09:52.702Z"},{"rank":29,"tracked_at":"2024-07-01T08:20:41.571Z"},{"rank":28,"tracked_at":"2024-07-01T08:29:14.784Z"},{"rank":27,"tracked_at":"2024-07-01T08:33:01.807Z"},{"rank":29,"tracked_at":"2024-07-01T08:40:33.038Z"},{"rank":28,"tracked_at":"2024-07-01T08:52:54.013Z"},{"rank":29,"tracked_at":"2024-07-01T08:55:00.559Z"},{"rank":31,"tracked_at":"2024-07-01T08:56:04.645Z"},{"rank":30,"tracked_at":"2024-07-01T08:58:44.895Z"},{"rank":28,"tracked_at":"2024-07-01T09:00:22.010Z"},{"rank":53,"tracked_at":"2024-07-01T09:00:56.030Z"},{"rank":54,"tracked_at":"2024-07-01T09:06:45.712Z"},{"rank":55,"tracked_at":"2024-07-01T09:16:25.033Z"},{"rank":56,"tracked_at":"2024-07-01T09:16:56.548Z"},{"rank":57,"tracked_at":"2024-07-01T09:17:27.727Z"},{"rank":56,"tracked_at":"2024-07-01T09:33:17.251Z"},{"rank":57,"tracked_at":"2024-07-01T09:33:48.538Z"},{"rank":58,"tracked_at":"2024-07-01T09:40:40.364Z"},{"rank":57,"tracked_at":"2024-07-01T09:45:56.716Z"},{"rank":58,"tracked_at":"2024-07-01T09:48:01.200Z"},{"rank":59,"tracked_at":"2024-07-01T09:49:37.306Z"},{"rank":58,"tracked_at":"2024-07-01T09:58:03.151Z"},{"rank":59,"tracked_at":"2024-07-01T10:02:21.464Z"},{"rank":60,"tracked_at":"2024-07-01T10:06:02.475Z"},{"rank":59,"tracked_at":"2024-07-01T10:06:35.612Z"},{"rank":60,"tracked_at":"2024-07-01T10:29:18.183Z"},{"rank":61,"tracked_at":"2024-07-01T10:35:52.717Z"},{"rank":60,"tracked_at":"2024-07-01T10:45:24.417Z"},{"rank":61,"tracked_at":"2024-07-01T10:51:44.782Z"},{"rank":62,"tracked_at":"2024-07-01T10:54:55.641Z"},{"rank":63,"tracked_at":"2024-07-01T11:00:12.486Z"},{"rank":62,"tracked_at":"2024-07-01T11:05:01.376Z"},{"rank":63,"tracked_at":"2024-07-01T11:09:14.481Z"},{"rank":64,"tracked_at":"2024-07-01T11:11:56.875Z"},{"rank":63,"tracked_at":"2024-07-01T11:26:49.114Z"},{"rank":62,"tracked_at":"2024-07-01T11:36:18.376Z"},{"rank":63,"tracked_at":"2024-07-01T11:43:14.600Z"},{"rank":64,"tracked_at":"2024-07-01T11:48:03.941Z"},{"rank":65,"tracked_at":"2024-07-01T11:48:35.257Z"},{"rank":66,"tracked_at":"2024-07-01T11:51:44.591Z"},{"rank":65,"tracked_at":"2024-07-01T11:53:19.129Z"},{"rank":67,"tracked_at":"2024-07-01T11:54:54.044Z"},{"rank":66,"tracked_at":"2024-07-01T11:55:26.647Z"},{"rank":67,"tracked_at":"2024-07-01T11:56:29.047Z"},{"rank":68,"tracked_at":"2024-07-01T12:00:42.200Z"},{"rank":69,"tracked_at":"2024-07-01T12:02:20.868Z"},{"rank":70,"tracked_at":"2024-07-01T12:03:54.527Z"},{"rank":71,"tracked_at":"2024-07-01T12:06:00.436Z"},{"rank":72,"tracked_at":"2024-07-01T12:06:31.764Z"},{"rank":73,"tracked_at":"2024-07-01T12:11:55.636Z"},{"rank":72,"tracked_at":"2024-07-01T12:12:27.327Z"},{"rank":73,"tracked_at":"2024-07-01T12:19:25.522Z"},{"rank":74,"tracked_at":"2024-07-01T12:26:54.922Z"},{"rank":75,"tracked_at":"2024-07-01T12:27:27.899Z"},{"rank":76,"tracked_at":"2024-07-01T12:30:09.351Z"},{"rank":75,"tracked_at":"2024-07-01T12:31:45.724Z"},{"rank":74,"tracked_at":"2024-07-01T12:34:24.923Z"},{"rank":73,"tracked_at":"2024-07-01T12:36:35.019Z"},{"rank":72,"tracked_at":"2024-07-01T12:38:45.039Z"},{"rank":71,"tracked_at":"2024-07-01T12:39:50.690Z"},{"rank":70,"tracked_at":"2024-07-01T12:40:55.085Z"},{"rank":71,"tracked_at":"2024-07-01T12:45:42.311Z"},{"rank":70,"tracked_at":"2024-07-01T12:51:11.229Z"},{"rank":71,"tracked_at":"2024-07-01T12:51:43.378Z"},{"rank":72,"tracked_at":"2024-07-01T12:52:15.611Z"},{"rank":73,"tracked_at":"2024-07-01T12:54:23.084Z"},{"rank":72,"tracked_at":"2024-07-01T12:56:33.660Z"},{"rank":71,"tracked_at":"2024-07-01T13:01:22.951Z"},{"rank":69,"tracked_at":"2024-07-01T13:01:55.843Z"},{"rank":68,"tracked_at":"2024-07-01T13:02:29.377Z"},{"rank":66,"tracked_at":"2024-07-01T13:03:01.787Z"},{"rank":65,"tracked_at":"2024-07-01T13:04:07.267Z"},{"rank":64,"tracked_at":"2024-07-01T13:10:44.582Z"},{"rank":65,"tracked_at":"2024-07-01T13:11:18.113Z"},{"rank":64,"tracked_at":"2024-07-01T13:13:30.492Z"},{"rank":65,"tracked_at":"2024-07-01T13:14:37.478Z"},{"rank":66,"tracked_at":"2024-07-01T13:20:04.010Z"},{"rank":65,"tracked_at":"2024-07-01T13:22:12.160Z"},{"rank":66,"tracked_at":"2024-07-01T13:26:05.333Z"},{"rank":65,"tracked_at":"2024-07-01T13:27:08.772Z"},{"rank":64,"tracked_at":"2024-07-01T13:29:17.669Z"},{"rank":65,"tracked_at":"2024-07-01T13:33:39.253Z"},{"rank":66,"tracked_at":"2024-07-01T13:34:12.100Z"},{"rank":65,"tracked_at":"2024-07-01T13:39:12.330Z"},{"rank":64,"tracked_at":"2024-07-01T13:39:44.299Z"},{"rank":65,"tracked_at":"2024-07-01T13:41:54.782Z"},{"rank":64,"tracked_at":"2024-07-01T13:42:26.930Z"},{"rank":63,"tracked_at":"2024-07-01T13:45:09.891Z"},{"rank":62,"tracked_at":"2024-07-01T13:46:14.446Z"},{"rank":61,"tracked_at":"2024-07-01T13:47:22.053Z"},{"rank":60,"tracked_at":"2024-07-01T13:56:57.327Z"},{"rank":59,"tracked_at":"2024-07-01T13:57:28.438Z"},{"rank":60,"tracked_at":"2024-07-01T13:59:08.618Z"},{"rank":59,"tracked_at":"2024-07-01T14:00:13.856Z"},{"rank":58,"tracked_at":"2024-07-01T14:08:29.922Z"},{"rank":59,"tracked_at":"2024-07-01T14:13:27.739Z"},{"rank":58,"tracked_at":"2024-07-01T14:15:03.365Z"},{"rank":59,"tracked_at":"2024-07-01T14:16:41.615Z"},{"rank":58,"tracked_at":"2024-07-01T14:17:17.107Z"},{"rank":57,"tracked_at":"2024-07-01T14:19:26.837Z"},{"rank":58,"tracked_at":"2024-07-01T14:23:16.558Z"},{"rank":57,"tracked_at":"2024-07-01T14:25:29.346Z"},{"rank":56,"tracked_at":"2024-07-01T14:26:06.612Z"},{"rank":57,"tracked_at":"2024-07-01T14:26:41.760Z"},{"rank":55,"tracked_at":"2024-07-01T14:30:32.361Z"},{"rank":54,"tracked_at":"2024-07-01T14:32:11.832Z"},{"rank":53,"tracked_at":"2024-07-01T14:37:04.824Z"},{"rank":54,"tracked_at":"2024-07-01T14:41:25.886Z"},{"rank":53,"tracked_at":"2024-07-01T14:41:58.674Z"},{"rank":52,"tracked_at":"2024-07-01T14:47:00.300Z"},{"rank":53,"tracked_at":"2024-07-01T14:50:19.339Z"},{"rank":52,"tracked_at":"2024-07-01T14:53:39.450Z"},{"rank":53,"tracked_at":"2024-07-01T14:54:45.627Z"},{"rank":54,"tracked_at":"2024-07-01T14:55:50.764Z"},{"rank":53,"tracked_at":"2024-07-01T14:56:25.493Z"},{"rank":52,"tracked_at":"2024-07-01T14:59:07.178Z"},{"rank":51,"tracked_at":"2024-07-01T15:01:57.295Z"},{"rank":52,"tracked_at":"2024-07-01T15:07:27.025Z"},{"rank":51,"tracked_at":"2024-07-01T15:08:03.367Z"},{"rank":52,"tracked_at":"2024-07-01T15:08:35.273Z"},{"rank":53,"tracked_at":"2024-07-01T15:12:59.363Z"},{"rank":52,"tracked_at":"2024-07-01T15:13:33.261Z"},{"rank":51,"tracked_at":"2024-07-01T15:18:04.483Z"},{"rank":52,"tracked_at":"2024-07-01T15:22:03.067Z"},{"rank":53,"tracked_at":"2024-07-01T15:22:36.962Z"},{"rank":54,"tracked_at":"2024-07-01T15:23:42.403Z"},{"rank":55,"tracked_at":"2024-07-01T15:28:40.302Z"},{"rank":56,"tracked_at":"2024-07-01T15:30:21.325Z"},{"rank":55,"tracked_at":"2024-07-01T15:30:56.674Z"},{"rank":54,"tracked_at":"2024-07-01T15:32:35.771Z"},{"rank":55,"tracked_at":"2024-07-01T15:34:12.387Z"},{"rank":56,"tracked_at":"2024-07-01T15:36:56.036Z"},{"rank":55,"tracked_at":"2024-07-01T15:40:10.569Z"},{"rank":54,"tracked_at":"2024-07-01T15:49:39.150Z"},{"rank":53,"tracked_at":"2024-07-01T15:51:16.708Z"},{"rank":54,"tracked_at":"2024-07-01T15:54:36.733Z"},{"rank":53,"tracked_at":"2024-07-01T15:59:28.307Z"},{"rank":52,"tracked_at":"2024-07-01T16:06:35.181Z"},{"rank":53,"tracked_at":"2024-07-01T16:07:08.618Z"},{"rank":54,"tracked_at":"2024-07-01T16:13:10.040Z"},{"rank":53,"tracked_at":"2024-07-01T16:15:57.138Z"},{"rank":54,"tracked_at":"2024-07-01T16:19:12.992Z"},{"rank":55,"tracked_at":"2024-07-01T16:20:20.849Z"},{"rank":56,"tracked_at":"2024-07-01T16:24:46.016Z"},{"rank":57,"tracked_at":"2024-07-01T16:27:31.147Z"},{"rank":58,"tracked_at":"2024-07-01T16:28:43.803Z"},{"rank":59,"tracked_at":"2024-07-01T16:29:16.228Z"},{"rank":60,"tracked_at":"2024-07-01T16:37:03.282Z"},{"rank":61,"tracked_at":"2024-07-01T16:40:25.164Z"},{"rank":62,"tracked_at":"2024-07-01T16:44:48.320Z"},{"rank":61,"tracked_at":"2024-07-01T16:50:18.284Z"},{"rank":62,"tracked_at":"2024-07-01T16:59:19.210Z"},{"rank":63,"tracked_at":"2024-07-01T17:06:30.176Z"},{"rank":62,"tracked_at":"2024-07-01T17:08:10.795Z"},{"rank":63,"tracked_at":"2024-07-01T17:10:23.205Z"},{"rank":62,"tracked_at":"2024-07-01T17:14:15.642Z"},{"rank":63,"tracked_at":"2024-07-01T17:14:50.773Z"},{"rank":64,"tracked_at":"2024-07-01T17:15:59.540Z"},{"rank":65,"tracked_at":"2024-07-01T17:17:08.554Z"},{"rank":66,"tracked_at":"2024-07-01T17:18:51.498Z"},{"rank":67,"tracked_at":"2024-07-01T17:22:15.450Z"},{"rank":68,"tracked_at":"2024-07-01T17:27:19.020Z"},{"rank":67,"tracked_at":"2024-07-01T17:28:24.234Z"},{"rank":65,"tracked_at":"2024-07-01T17:28:56.413Z"},{"rank":67,"tracked_at":"2024-07-01T17:30:00.838Z"},{"rank":68,"tracked_at":"2024-07-01T17:31:09.539Z"},{"rank":67,"tracked_at":"2024-07-01T17:32:48.633Z"},{"rank":66,"tracked_at":"2024-07-01T17:35:02.534Z"},{"rank":67,"tracked_at":"2024-07-01T17:35:38.218Z"},{"rank":69,"tracked_at":"2024-07-01T17:36:43.704Z"},{"rank":70,"tracked_at":"2024-07-01T17:37:15.885Z"},{"rank":71,"tracked_at":"2024-07-01T17:40:00.060Z"},{"rank":70,"tracked_at":"2024-07-01T17:41:06.470Z"},{"rank":71,"tracked_at":"2024-07-01T17:43:18.540Z"},{"rank":72,"tracked_at":"2024-07-01T17:43:53.206Z"},{"rank":70,"tracked_at":"2024-07-01T17:45:34.318Z"},{"rank":71,"tracked_at":"2024-07-01T17:51:02.990Z"},{"rank":70,"tracked_at":"2024-07-01T17:57:49.157Z"},{"rank":69,"tracked_at":"2024-07-01T18:00:08.580Z"},{"rank":70,"tracked_at":"2024-07-01T18:01:50.598Z"},{"rank":71,"tracked_at":"2024-07-01T18:04:04.557Z"},{"rank":69,"tracked_at":"2024-07-01T18:06:16.719Z"},{"rank":68,"tracked_at":"2024-07-01T18:06:51.640Z"},{"rank":67,"tracked_at":"2024-07-01T18:08:34.818Z"},{"rank":68,"tracked_at":"2024-07-01T18:12:31.971Z"},{"rank":69,"tracked_at":"2024-07-01T18:16:30.549Z"},{"rank":68,"tracked_at":"2024-07-01T18:19:48.746Z"},{"rank":69,"tracked_at":"2024-07-01T18:23:10.472Z"},{"rank":68,"tracked_at":"2024-07-01T18:23:45.985Z"},{"rank":69,"tracked_at":"2024-07-01T18:24:53.003Z"},{"rank":67,"tracked_at":"2024-07-01T18:26:04.118Z"},{"rank":69,"tracked_at":"2024-07-01T18:30:31.790Z"},{"rank":70,"tracked_at":"2024-07-01T18:38:05.217Z"},{"rank":71,"tracked_at":"2024-07-01T18:39:12.931Z"},{"rank":72,"tracked_at":"2024-07-01T18:41:34.697Z"},{"rank":70,"tracked_at":"2024-07-01T18:45:02.092Z"},{"rank":31,"tracked_at":"2024-07-01T18:46:15.427Z"},{"rank":68,"tracked_at":"2024-07-01T18:46:54.871Z"},{"rank":67,"tracked_at":"2024-07-01T18:48:09.798Z"},{"rank":65,"tracked_at":"2024-07-01T18:51:35.200Z"},{"rank":67,"tracked_at":"2024-07-01T18:58:46.198Z"},{"rank":68,"tracked_at":"2024-07-01T19:00:30.614Z"},{"rank":69,"tracked_at":"2024-07-01T19:08:47.324Z"},{"rank":68,"tracked_at":"2024-07-01T19:14:39.110Z"},{"rank":67,"tracked_at":"2024-07-01T19:34:20.457Z"},{"rank":70,"tracked_at":"2024-07-01T19:34:52.472Z"},{"rank":69,"tracked_at":"2024-07-01T19:37:12.148Z"},{"rank":70,"tracked_at":"2024-07-01T19:41:11.546Z"},{"rank":71,"tracked_at":"2024-07-01T19:41:45.318Z"},{"rank":72,"tracked_at":"2024-07-01T19:42:22.857Z"},{"rank":73,"tracked_at":"2024-07-01T19:45:23.718Z"},{"rank":74,"tracked_at":"2024-07-01T19:45:57.854Z"},{"rank":75,"tracked_at":"2024-07-01T19:46:33.630Z"},{"rank":76,"tracked_at":"2024-07-01T19:51:42.143Z"},{"rank":77,"tracked_at":"2024-07-01T19:58:09.881Z"},{"rank":76,"tracked_at":"2024-07-01T20:13:43.485Z"},{"rank":75,"tracked_at":"2024-07-01T20:18:25.568Z"},{"rank":74,"tracked_at":"2024-07-01T20:20:11.326Z"},{"rank":77,"tracked_at":"2024-07-01T20:23:52.582Z"},{"rank":76,"tracked_at":"2024-07-01T20:26:06.968Z"},{"rank":75,"tracked_at":"2024-07-01T20:30:00.371Z"},{"rank":76,"tracked_at":"2024-07-01T20:33:21.814Z"},{"rank":77,"tracked_at":"2024-07-01T20:33:55.122Z"},{"rank":78,"tracked_at":"2024-07-01T20:40:47.196Z"},{"rank":79,"tracked_at":"2024-07-01T20:41:20.819Z"},{"rank":80,"tracked_at":"2024-07-01T20:45:24.131Z"},{"rank":81,"tracked_at":"2024-07-01T20:51:44.333Z"},{"rank":80,"tracked_at":"2024-07-01T20:56:13.645Z"},{"rank":81,"tracked_at":"2024-07-01T21:00:20.191Z"},{"rank":82,"tracked_at":"2024-07-01T21:02:48.778Z"},{"rank":81,"tracked_at":"2024-07-01T21:04:33.246Z"},{"rank":82,"tracked_at":"2024-07-01T21:10:25.269Z"},{"rank":81,"tracked_at":"2024-07-01T21:16:35.914Z"},{"rank":80,"tracked_at":"2024-07-01T21:19:22.857Z"},{"rank":81,"tracked_at":"2024-07-01T21:28:42.146Z"},{"rank":80,"tracked_at":"2024-07-01T21:31:35.587Z"},{"rank":82,"tracked_at":"2024-07-01T21:33:57.881Z"},{"rank":83,"tracked_at":"2024-07-01T21:34:30.250Z"},{"rank":84,"tracked_at":"2024-07-01T21:37:54.293Z"},{"rank":85,"tracked_at":"2024-07-01T21:38:26.503Z"},{"rank":86,"tracked_at":"2024-07-01T21:40:06.933Z"},{"rank":87,"tracked_at":"2024-07-01T21:42:21.113Z"},{"rank":88,"tracked_at":"2024-07-01T21:42:53.493Z"},{"rank":89,"tracked_at":"2024-07-01T21:43:30.417Z"},{"rank":88,"tracked_at":"2024-07-01T21:44:36.103Z"},{"rank":87,"tracked_at":"2024-07-01T21:47:24.098Z"},{"rank":86,"tracked_at":"2024-07-01T21:52:27.115Z"},{"rank":87,"tracked_at":"2024-07-01T21:59:52.831Z"},{"rank":88,"tracked_at":"2024-07-01T22:07:42.004Z"},{"rank":89,"tracked_at":"2024-07-01T22:08:14.507Z"},{"rank":91,"tracked_at":"2024-07-01T22:09:25.492Z"},{"rank":90,"tracked_at":"2024-07-01T22:11:39.245Z"},{"rank":91,"tracked_at":"2024-07-01T22:12:12.656Z"},{"rank":92,"tracked_at":"2024-07-01T22:22:12.288Z"},{"rank":93,"tracked_at":"2024-07-01T22:25:36.690Z"},{"rank":94,"tracked_at":"2024-07-01T22:26:42.292Z"},{"rank":93,"tracked_at":"2024-07-01T22:27:14.330Z"},{"rank":92,"tracked_at":"2024-07-01T22:33:12.202Z"},{"rank":94,"tracked_at":"2024-07-01T22:34:19.312Z"},{"rank":93,"tracked_at":"2024-07-01T22:36:34.037Z"},{"rank":92,"tracked_at":"2024-07-01T22:37:40.676Z"},{"rank":93,"tracked_at":"2024-07-01T22:44:49.033Z"},{"rank":94,"tracked_at":"2024-07-01T22:47:31.895Z"},{"rank":95,"tracked_at":"2024-07-01T22:50:13.097Z"},{"rank":96,"tracked_at":"2024-07-01T22:58:25.819Z"},{"rank":95,"tracked_at":"2024-07-01T23:00:33.460Z"},{"rank":94,"tracked_at":"2024-07-01T23:15:37.495Z"},{"rank":93,"tracked_at":"2024-07-01T23:19:58.593Z"},{"rank":92,"tracked_at":"2024-07-01T23:21:37.928Z"},{"rank":93,"tracked_at":"2024-07-01T23:23:47.778Z"},{"rank":94,"tracked_at":"2024-07-01T23:28:17.976Z"},{"rank":95,"tracked_at":"2024-07-01T23:29:54.618Z"},{"rank":96,"tracked_at":"2024-07-01T23:32:36.433Z"},{"rank":97,"tracked_at":"2024-07-01T23:33:39.780Z"},{"rank":98,"tracked_at":"2024-07-01T23:34:11.500Z"},{"rank":97,"tracked_at":"2024-07-01T23:35:16.121Z"},{"rank":99,"tracked_at":"2024-07-01T23:35:51.503Z"},{"rank":98,"tracked_at":"2024-07-01T23:42:27.060Z"},{"rank":96,"tracked_at":"2024-07-01T23:43:02.762Z"},{"rank":97,"tracked_at":"2024-07-01T23:45:43.979Z"},{"rank":98,"tracked_at":"2024-07-01T23:46:18.364Z"},{"rank":100,"tracked_at":"2024-07-01T23:46:50.692Z"},{"rank":101,"tracked_at":"2024-07-01T23:48:28.925Z"},{"rank":102,"tracked_at":"2024-07-01T23:49:34.450Z"},{"rank":103,"tracked_at":"2024-07-01T23:50:11.775Z"},{"rank":104,"tracked_at":"2024-07-01T23:52:52.095Z"},{"rank":105,"tracked_at":"2024-07-01T23:53:23.556Z"},{"rank":106,"tracked_at":"2024-07-01T23:55:03.247Z"},{"rank":107,"tracked_at":"2024-07-01T23:55:37.538Z"},{"rank":108,"tracked_at":"2024-07-01T23:56:10.933Z"},{"rank":109,"tracked_at":"2024-07-02T00:06:37.586Z"},{"rank":110,"tracked_at":"2024-07-02T00:08:50.956Z"},{"rank":111,"tracked_at":"2024-07-02T00:14:14.546Z"},{"rank":109,"tracked_at":"2024-07-02T00:15:49.502Z"},{"rank":108,"tracked_at":"2024-07-02T00:29:50.969Z"},{"rank":109,"tracked_at":"2024-07-02T00:34:39.849Z"},{"rank":110,"tracked_at":"2024-07-02T00:36:47.894Z"},{"rank":109,"tracked_at":"2024-07-02T00:44:56.100Z"},{"rank":110,"tracked_at":"2024-07-02T00:48:46.929Z"},{"rank":109,"tracked_at":"2024-07-02T00:49:20.058Z"},{"rank":110,"tracked_at":"2024-07-02T00:52:38.852Z"},{"rank":109,"tracked_at":"2024-07-02T01:06:40.597Z"},{"rank":108,"tracked_at":"2024-07-02T01:15:12.983Z"},{"rank":109,"tracked_at":"2024-07-02T01:20:01.918Z"},{"rank":110,"tracked_at":"2024-07-02T01:23:18.717Z"},{"rank":111,"tracked_at":"2024-07-02T01:28:07.653Z"},{"rank":112,"tracked_at":"2024-07-02T01:32:20.410Z"},{"rank":114,"tracked_at":"2024-07-02T01:32:52.597Z"},{"rank":113,"tracked_at":"2024-07-02T01:35:00.370Z"},{"rank":114,"tracked_at":"2024-07-02T01:36:34.632Z"},{"rank":113,"tracked_at":"2024-07-02T01:38:10.352Z"},{"rank":114,"tracked_at":"2024-07-02T01:40:50.386Z"},{"rank":116,"tracked_at":"2024-07-02T01:43:00.075Z"},{"rank":117,"tracked_at":"2024-07-02T01:44:04.151Z"},{"rank":118,"tracked_at":"2024-07-02T01:50:58.469Z"},{"rank":119,"tracked_at":"2024-07-02T01:53:06.368Z"},{"rank":120,"tracked_at":"2024-07-02T01:54:42.392Z"},{"rank":121,"tracked_at":"2024-07-02T01:55:14.925Z"},{"rank":120,"tracked_at":"2024-07-02T02:00:07.295Z"},{"rank":119,"tracked_at":"2024-07-02T02:04:26.561Z"},{"rank":120,"tracked_at":"2024-07-02T02:07:03.159Z"},{"rank":121,"tracked_at":"2024-07-02T02:07:34.520Z"},{"rank":120,"tracked_at":"2024-07-02T02:21:30.315Z"},{"rank":121,"tracked_at":"2024-07-02T02:26:52.400Z"},{"rank":122,"tracked_at":"2024-07-02T02:30:43.602Z"},{"rank":121,"tracked_at":"2024-07-02T02:32:50.174Z"},{"rank":120,"tracked_at":"2024-07-02T02:37:07.535Z"},{"rank":119,"tracked_at":"2024-07-02T02:42:57.727Z"},{"rank":120,"tracked_at":"2024-07-02T02:51:08.504Z"},{"rank":118,"tracked_at":"2024-07-02T02:52:43.672Z"},{"rank":119,"tracked_at":"2024-07-02T02:57:00.212Z"},{"rank":120,"tracked_at":"2024-07-02T02:58:37.061Z"},{"rank":121,"tracked_at":"2024-07-02T02:59:44.853Z"},{"rank":114,"tracked_at":"2024-07-02T03:03:23.296Z"},{"rank":115,"tracked_at":"2024-07-02T03:09:12.506Z"},{"rank":114,"tracked_at":"2024-07-02T03:16:01.496Z"},{"rank":113,"tracked_at":"2024-07-02T03:16:34.255Z"},{"rank":114,"tracked_at":"2024-07-02T03:24:38.737Z"},{"rank":116,"tracked_at":"2024-07-02T03:25:42.973Z"},{"rank":117,"tracked_at":"2024-07-02T03:26:14.527Z"},{"rank":116,"tracked_at":"2024-07-02T03:32:05.028Z"},{"rank":115,"tracked_at":"2024-07-02T03:39:29.211Z"},{"rank":114,"tracked_at":"2024-07-02T03:41:36.455Z"},{"rank":113,"tracked_at":"2024-07-02T03:48:29.913Z"},{"rank":112,"tracked_at":"2024-07-02T03:52:15.998Z"},{"rank":113,"tracked_at":"2024-07-02T03:53:19.149Z"},{"rank":114,"tracked_at":"2024-07-02T03:57:03.741Z"},{"rank":115,"tracked_at":"2024-07-02T04:01:16.854Z"},{"rank":114,"tracked_at":"2024-07-02T04:02:22.628Z"},{"rank":115,"tracked_at":"2024-07-02T04:05:02.421Z"},{"rank":114,"tracked_at":"2024-07-02T04:09:57.183Z"},{"rank":115,"tracked_at":"2024-07-02T04:10:29.832Z"},{"rank":114,"tracked_at":"2024-07-02T04:15:50.428Z"},{"rank":113,"tracked_at":"2024-07-02T04:19:04.398Z"},{"rank":114,"tracked_at":"2024-07-02T04:20:38.403Z"},{"rank":115,"tracked_at":"2024-07-02T04:28:34.127Z"},{"rank":116,"tracked_at":"2024-07-02T04:30:09.020Z"},{"rank":117,"tracked_at":"2024-07-02T04:30:40.488Z"},{"rank":116,"tracked_at":"2024-07-02T04:31:44.396Z"},{"rank":117,"tracked_at":"2024-07-02T04:39:46.866Z"},{"rank":116,"tracked_at":"2024-07-02T04:41:23.244Z"},{"rank":115,"tracked_at":"2024-07-02T04:44:05.129Z"},{"rank":114,"tracked_at":"2024-07-02T04:44:38.519Z"},{"rank":115,"tracked_at":"2024-07-02T04:48:21.323Z"},{"rank":114,"tracked_at":"2024-07-02T04:58:57.522Z"},{"rank":113,"tracked_at":"2024-07-02T05:02:06.436Z"},{"rank":112,"tracked_at":"2024-07-02T05:05:15.223Z"},{"rank":111,"tracked_at":"2024-07-02T05:06:19.394Z"},{"rank":110,"tracked_at":"2024-07-02T05:14:14.705Z"},{"rank":109,"tracked_at":"2024-07-02T05:19:33.843Z"},{"rank":108,"tracked_at":"2024-07-02T05:24:23.536Z"},{"rank":109,"tracked_at":"2024-07-02T05:38:45.866Z"},{"rank":110,"tracked_at":"2024-07-02T05:45:37.053Z"},{"rank":109,"tracked_at":"2024-07-02T05:48:48.824Z"},{"rank":110,"tracked_at":"2024-07-02T05:51:27.228Z"},{"rank":109,"tracked_at":"2024-07-02T05:56:41.397Z"},{"rank":110,"tracked_at":"2024-07-02T06:00:22.933Z"},{"rank":111,"tracked_at":"2024-07-02T06:09:23.646Z"},{"rank":109,"tracked_at":"2024-07-02T06:20:01.387Z"},{"rank":108,"tracked_at":"2024-07-02T06:20:34.318Z"},{"rank":107,"tracked_at":"2024-07-02T06:21:39.587Z"},{"rank":106,"tracked_at":"2024-07-02T06:32:27.009Z"},{"rank":107,"tracked_at":"2024-07-02T07:00:37.677Z"},{"rank":108,"tracked_at":"2024-07-02T07:11:09.820Z"},{"rank":109,"tracked_at":"2024-07-02T07:32:52.236Z"},{"rank":108,"tracked_at":"2024-07-02T07:38:16.332Z"},{"rank":107,"tracked_at":"2024-07-02T07:44:43.022Z"},{"rank":108,"tracked_at":"2024-07-02T07:53:28.454Z"},{"rank":107,"tracked_at":"2024-07-02T07:56:47.150Z"},{"rank":106,"tracked_at":"2024-07-02T07:59:57.738Z"},{"rank":105,"tracked_at":"2024-07-02T08:03:45.863Z"},{"rank":104,"tracked_at":"2024-07-02T08:19:45.351Z"},{"rank":105,"tracked_at":"2024-07-02T08:42:09.863Z"},{"rank":106,"tracked_at":"2024-07-02T09:21:03.421Z"},{"rank":107,"tracked_at":"2024-07-02T09:22:38.609Z"},{"rank":108,"tracked_at":"2024-07-02T09:23:11.207Z"},{"rank":107,"tracked_at":"2024-07-02T09:26:50.833Z"},{"rank":108,"tracked_at":"2024-07-02T09:28:25.909Z"},{"rank":107,"tracked_at":"2024-07-02T09:46:53.647Z"},{"rank":106,"tracked_at":"2024-07-02T09:55:50.459Z"},{"rank":107,"tracked_at":"2024-07-02T10:15:21.163Z"},{"rank":106,"tracked_at":"2024-07-02T10:16:57.022Z"},{"rank":107,"tracked_at":"2024-07-02T10:33:24.723Z"},{"rank":106,"tracked_at":"2024-07-02T10:44:01.374Z"},{"rank":107,"tracked_at":"2024-07-02T10:45:35.349Z"},{"rank":108,"tracked_at":"2024-07-02T10:49:13.418Z"},{"rank":109,"tracked_at":"2024-07-02T10:58:21.795Z"},{"rank":108,"tracked_at":"2024-07-02T11:14:54.548Z"},{"rank":107,"tracked_at":"2024-07-02T11:49:18.681Z"},{"rank":108,"tracked_at":"2024-07-02T11:50:23.533Z"},{"rank":109,"tracked_at":"2024-07-02T11:50:55.133Z"},{"rank":110,"tracked_at":"2024-07-02T12:01:50.612Z"},{"rank":111,"tracked_at":"2024-07-02T12:13:09.650Z"},{"rank":112,"tracked_at":"2024-07-02T12:19:08.010Z"},{"rank":111,"tracked_at":"2024-07-02T12:22:53.903Z"},{"rank":113,"tracked_at":"2024-07-02T12:27:11.763Z"},{"rank":114,"tracked_at":"2024-07-02T12:27:43.944Z"},{"rank":113,"tracked_at":"2024-07-02T12:29:20.553Z"},{"rank":114,"tracked_at":"2024-07-02T12:35:19.576Z"},{"rank":115,"tracked_at":"2024-07-02T12:37:29.729Z"},{"rank":114,"tracked_at":"2024-07-02T12:45:12.673Z"},{"rank":113,"tracked_at":"2024-07-02T12:49:05.563Z"},{"rank":114,"tracked_at":"2024-07-02T13:01:13.239Z"},{"rank":115,"tracked_at":"2024-07-02T13:02:18.929Z"},{"rank":117,"tracked_at":"2024-07-02T13:08:22.486Z"},{"rank":118,"tracked_at":"2024-07-02T13:12:47.091Z"},{"rank":119,"tracked_at":"2024-07-02T13:14:32.905Z"},{"rank":120,"tracked_at":"2024-07-02T13:16:12.357Z"},{"rank":121,"tracked_at":"2024-07-02T13:16:44.795Z"},{"rank":122,"tracked_at":"2024-07-02T13:17:18.400Z"},{"rank":123,"tracked_at":"2024-07-02T13:21:12.467Z"},{"rank":124,"tracked_at":"2024-07-02T13:22:18.990Z"},{"rank":122,"tracked_at":"2024-07-02T13:22:54.109Z"},{"rank":121,"tracked_at":"2024-07-02T13:35:48.217Z"},{"rank":123,"tracked_at":"2024-07-02T13:39:05.118Z"},{"rank":124,"tracked_at":"2024-07-02T13:39:39.144Z"},{"rank":123,"tracked_at":"2024-07-02T13:57:33.267Z"},{"rank":124,"tracked_at":"2024-07-02T13:59:49.295Z"},{"rank":125,"tracked_at":"2024-07-02T14:02:00.335Z"},{"rank":126,"tracked_at":"2024-07-02T14:02:33.001Z"},{"rank":128,"tracked_at":"2024-07-02T14:03:06.350Z"},{"rank":129,"tracked_at":"2024-07-02T14:03:41.623Z"},{"rank":128,"tracked_at":"2024-07-02T14:04:50.979Z"},{"rank":129,"tracked_at":"2024-07-02T14:08:47.917Z"},{"rank":130,"tracked_at":"2024-07-02T14:13:54.953Z"},{"rank":129,"tracked_at":"2024-07-02T14:17:49.203Z"},{"rank":128,"tracked_at":"2024-07-02T14:20:04.155Z"},{"rank":126,"tracked_at":"2024-07-02T14:20:37.787Z"},{"rank":127,"tracked_at":"2024-07-02T14:21:14.147Z"},{"rank":126,"tracked_at":"2024-07-02T14:31:16.484Z"},{"rank":127,"tracked_at":"2024-07-02T14:36:46.107Z"},{"rank":128,"tracked_at":"2024-07-02T14:37:18.074Z"},{"rank":129,"tracked_at":"2024-07-02T14:43:30.988Z"},{"rank":128,"tracked_at":"2024-07-02T14:44:36.509Z"},{"rank":129,"tracked_at":"2024-07-02T14:46:45.434Z"},{"rank":130,"tracked_at":"2024-07-02T14:48:27.123Z"},{"rank":131,"tracked_at":"2024-07-02T14:50:07.707Z"},{"rank":132,"tracked_at":"2024-07-02T14:50:44.709Z"},{"rank":133,"tracked_at":"2024-07-02T14:53:02.157Z"},{"rank":132,"tracked_at":"2024-07-02T14:53:34.270Z"},{"rank":133,"tracked_at":"2024-07-02T14:56:22.878Z"},{"rank":134,"tracked_at":"2024-07-02T14:56:56.641Z"},{"rank":135,"tracked_at":"2024-07-02T14:58:00.047Z"},{"rank":134,"tracked_at":"2024-07-02T14:59:04.679Z"},{"rank":135,"tracked_at":"2024-07-02T15:02:21.628Z"},{"rank":136,"tracked_at":"2024-07-02T15:02:56.186Z"},{"rank":137,"tracked_at":"2024-07-02T15:05:43.364Z"},{"rank":136,"tracked_at":"2024-07-02T15:07:18.853Z"},{"rank":137,"tracked_at":"2024-07-02T15:08:23.986Z"},{"rank":138,"tracked_at":"2024-07-02T15:09:31.099Z"},{"rank":139,"tracked_at":"2024-07-02T15:14:27.337Z"},{"rank":140,"tracked_at":"2024-07-02T15:17:14.382Z"},{"rank":141,"tracked_at":"2024-07-02T15:17:49.394Z"},{"rank":140,"tracked_at":"2024-07-02T15:19:00.941Z"},{"rank":141,"tracked_at":"2024-07-02T15:23:28.483Z"},{"rank":142,"tracked_at":"2024-07-02T15:28:30.674Z"},{"rank":143,"tracked_at":"2024-07-02T15:29:04.006Z"},{"rank":144,"tracked_at":"2024-07-02T15:31:50.121Z"},{"rank":146,"tracked_at":"2024-07-02T15:33:29.732Z"},{"rank":145,"tracked_at":"2024-07-02T15:38:56.216Z"},{"rank":144,"tracked_at":"2024-07-02T15:41:48.167Z"},{"rank":143,"tracked_at":"2024-07-02T15:46:20.167Z"},{"rank":142,"tracked_at":"2024-07-02T15:47:26.232Z"},{"rank":143,"tracked_at":"2024-07-02T15:48:29.359Z"},{"rank":142,"tracked_at":"2024-07-02T15:50:39.759Z"},{"rank":143,"tracked_at":"2024-07-02T15:52:50.177Z"},{"rank":144,"tracked_at":"2024-07-02T15:57:57.353Z"},{"rank":145,"tracked_at":"2024-07-02T15:58:29.565Z"},{"rank":144,"tracked_at":"2024-07-02T16:06:14.442Z"},{"rank":143,"tracked_at":"2024-07-02T16:07:51.792Z"},{"rank":142,"tracked_at":"2024-07-02T16:12:46.884Z"},{"rank":143,"tracked_at":"2024-07-02T16:20:32.732Z"},{"rank":144,"tracked_at":"2024-07-02T16:23:16.010Z"},{"rank":146,"tracked_at":"2024-07-02T16:23:50.053Z"},{"rank":144,"tracked_at":"2024-07-02T16:24:24.085Z"},{"rank":143,"tracked_at":"2024-07-02T16:24:58.315Z"},{"rank":142,"tracked_at":"2024-07-02T16:25:31.739Z"},{"rank":143,"tracked_at":"2024-07-02T16:30:02.225Z"},{"rank":141,"tracked_at":"2024-07-02T16:31:10.364Z"},{"rank":140,"tracked_at":"2024-07-02T16:31:42.862Z"},{"rank":141,"tracked_at":"2024-07-02T16:38:44.551Z"},{"rank":142,"tracked_at":"2024-07-02T16:41:26.353Z"},{"rank":141,"tracked_at":"2024-07-02T16:50:10.483Z"},{"rank":140,"tracked_at":"2024-07-02T16:52:52.229Z"},{"rank":141,"tracked_at":"2024-07-02T16:56:42.562Z"},{"rank":143,"tracked_at":"2024-07-02T16:58:21.125Z"},{"rank":142,"tracked_at":"2024-07-02T16:59:30.217Z"},{"rank":143,"tracked_at":"2024-07-02T17:00:03.158Z"},{"rank":144,"tracked_at":"2024-07-02T17:00:48.430Z"},{"rank":142,"tracked_at":"2024-07-02T17:04:20.892Z"},{"rank":141,"tracked_at":"2024-07-02T17:05:58.756Z"},{"rank":142,"tracked_at":"2024-07-02T17:07:38.207Z"},{"rank":141,"tracked_at":"2024-07-02T17:08:43.799Z"},{"rank":140,"tracked_at":"2024-07-02T17:09:17.684Z"},{"rank":141,"tracked_at":"2024-07-02T17:09:48.960Z"},{"rank":140,"tracked_at":"2024-07-02T17:10:22.441Z"},{"rank":139,"tracked_at":"2024-07-02T17:12:00.478Z"},{"rank":138,"tracked_at":"2024-07-02T17:13:09.823Z"},{"rank":139,"tracked_at":"2024-07-02T17:19:17.204Z"},{"rank":140,"tracked_at":"2024-07-02T17:20:23.050Z"},{"rank":139,"tracked_at":"2024-07-02T17:22:06.840Z"},{"rank":141,"tracked_at":"2024-07-02T17:25:25.273Z"},{"rank":142,"tracked_at":"2024-07-02T17:26:28.197Z"},{"rank":141,"tracked_at":"2024-07-02T17:29:47.106Z"},{"rank":140,"tracked_at":"2024-07-02T17:31:24.190Z"},{"rank":141,"tracked_at":"2024-07-02T17:31:57.614Z"},{"rank":140,"tracked_at":"2024-07-02T17:40:16.036Z"},{"rank":141,"tracked_at":"2024-07-02T17:41:54.281Z"},{"rank":140,"tracked_at":"2024-07-02T17:44:08.144Z"},{"rank":141,"tracked_at":"2024-07-02T17:45:15.350Z"},{"rank":142,"tracked_at":"2024-07-02T17:46:26.730Z"},{"rank":141,"tracked_at":"2024-07-02T17:49:10.762Z"},{"rank":142,"tracked_at":"2024-07-02T17:51:21.238Z"},{"rank":143,"tracked_at":"2024-07-02T17:55:48.314Z"},{"rank":142,"tracked_at":"2024-07-02T18:01:29.040Z"},{"rank":141,"tracked_at":"2024-07-02T18:05:22.853Z"},{"rank":140,"tracked_at":"2024-07-02T18:06:27.480Z"},{"rank":139,"tracked_at":"2024-07-02T18:07:01.396Z"},{"rank":138,"tracked_at":"2024-07-02T18:09:44.145Z"},{"rank":139,"tracked_at":"2024-07-02T18:16:15.747Z"},{"rank":138,"tracked_at":"2024-07-02T18:18:25.147Z"},{"rank":137,"tracked_at":"2024-07-02T18:19:39.507Z"},{"rank":138,"tracked_at":"2024-07-02T18:25:15.104Z"},{"rank":139,"tracked_at":"2024-07-02T18:25:52.448Z"},{"rank":142,"tracked_at":"2024-07-02T18:28:07.273Z"},{"rank":143,"tracked_at":"2024-07-02T18:30:55.167Z"},{"rank":144,"tracked_at":"2024-07-02T18:31:27.447Z"},{"rank":143,"tracked_at":"2024-07-02T18:38:01.017Z"},{"rank":144,"tracked_at":"2024-07-02T18:41:12.143Z"},{"rank":143,"tracked_at":"2024-07-02T18:43:24.492Z"},{"rank":142,"tracked_at":"2024-07-02T18:45:40.759Z"},{"rank":141,"tracked_at":"2024-07-02T18:57:39.454Z"},{"rank":143,"tracked_at":"2024-07-02T19:08:11.421Z"},{"rank":144,"tracked_at":"2024-07-02T19:08:45.209Z"},{"rank":145,"tracked_at":"2024-07-02T19:13:13.524Z"},{"rank":144,"tracked_at":"2024-07-02T19:14:19.741Z"},{"rank":145,"tracked_at":"2024-07-02T19:14:56.231Z"},{"rank":144,"tracked_at":"2024-07-02T19:21:46.523Z"},{"rank":143,"tracked_at":"2024-07-02T19:24:31.014Z"},{"rank":144,"tracked_at":"2024-07-02T19:27:24.777Z"},{"rank":145,"tracked_at":"2024-07-02T19:29:36.058Z"},{"rank":144,"tracked_at":"2024-07-02T19:34:39.061Z"},{"rank":143,"tracked_at":"2024-07-02T19:39:19.461Z"},{"rank":144,"tracked_at":"2024-07-02T19:40:57.255Z"},{"rank":143,"tracked_at":"2024-07-02T19:42:04.137Z"},{"rank":142,"tracked_at":"2024-07-02T19:46:55.458Z"},{"rank":141,"tracked_at":"2024-07-02T19:58:28.622Z"},{"rank":140,"tracked_at":"2024-07-02T20:07:09.191Z"},{"rank":139,"tracked_at":"2024-07-02T20:08:13.657Z"},{"rank":140,"tracked_at":"2024-07-02T20:09:53.099Z"},{"rank":141,"tracked_at":"2024-07-02T20:11:28.795Z"},{"rank":142,"tracked_at":"2024-07-02T20:15:53.068Z"},{"rank":143,"tracked_at":"2024-07-02T20:18:01.993Z"},{"rank":144,"tracked_at":"2024-07-02T20:22:21.041Z"},{"rank":145,"tracked_at":"2024-07-02T20:27:16.354Z"},{"rank":146,"tracked_at":"2024-07-02T20:29:24.745Z"},{"rank":147,"tracked_at":"2024-07-02T20:31:04.297Z"},{"rank":146,"tracked_at":"2024-07-02T20:32:47.344Z"},{"rank":147,"tracked_at":"2024-07-02T20:42:08.489Z"},{"rank":148,"tracked_at":"2024-07-02T20:43:12.850Z"},{"rank":147,"tracked_at":"2024-07-02T20:47:35.989Z"},{"rank":148,"tracked_at":"2024-07-02T20:49:47.307Z"},{"rank":149,"tracked_at":"2024-07-02T21:04:04.220Z"},{"rank":150,"tracked_at":"2024-07-02T21:05:43.795Z"},{"rank":151,"tracked_at":"2024-07-02T21:08:29.858Z"},{"rank":152,"tracked_at":"2024-07-02T21:09:02.147Z"},{"rank":153,"tracked_at":"2024-07-02T21:11:51.414Z"},{"rank":152,"tracked_at":"2024-07-02T21:12:58.177Z"},{"rank":154,"tracked_at":"2024-07-02T21:18:23.774Z"},{"rank":153,"tracked_at":"2024-07-02T21:24:54.819Z"},{"rank":152,"tracked_at":"2024-07-02T21:27:07.581Z"},{"rank":153,"tracked_at":"2024-07-02T21:30:59.840Z"},{"rank":152,"tracked_at":"2024-07-02T21:32:39.610Z"},{"rank":155,"tracked_at":"2024-07-02T21:38:47.278Z"},{"rank":154,"tracked_at":"2024-07-02T21:41:00.485Z"},{"rank":153,"tracked_at":"2024-07-02T21:44:54.294Z"},{"rank":152,"tracked_at":"2024-07-02T21:48:17.887Z"},{"rank":153,"tracked_at":"2024-07-02T21:48:54.003Z"},{"rank":154,"tracked_at":"2024-07-02T21:51:09.357Z"},{"rank":155,"tracked_at":"2024-07-02T21:53:21.966Z"},{"rank":154,"tracked_at":"2024-07-02T21:56:47.226Z"},{"rank":155,"tracked_at":"2024-07-02T21:57:20.978Z"},{"rank":156,"tracked_at":"2024-07-02T22:03:52.042Z"},{"rank":157,"tracked_at":"2024-07-02T22:04:24.331Z"},{"rank":158,"tracked_at":"2024-07-02T22:14:19.119Z"},{"rank":157,"tracked_at":"2024-07-02T22:19:21.533Z"},{"rank":158,"tracked_at":"2024-07-02T22:24:50.344Z"},{"rank":157,"tracked_at":"2024-07-02T22:25:23.432Z"},{"rank":159,"tracked_at":"2024-07-02T22:31:22.484Z"},{"rank":160,"tracked_at":"2024-07-02T22:33:00.527Z"},{"rank":159,"tracked_at":"2024-07-02T22:35:45.488Z"},{"rank":160,"tracked_at":"2024-07-02T22:36:19.877Z"},{"rank":161,"tracked_at":"2024-07-02T22:37:25.042Z"},{"rank":162,"tracked_at":"2024-07-02T22:37:56.825Z"},{"rank":161,"tracked_at":"2024-07-02T22:40:06.447Z"},{"rank":160,"tracked_at":"2024-07-02T22:45:33.550Z"},{"rank":159,"tracked_at":"2024-07-02T22:54:46.920Z"},{"rank":158,"tracked_at":"2024-07-02T22:56:23.056Z"},{"rank":157,"tracked_at":"2024-07-02T22:59:32.506Z"},{"rank":158,"tracked_at":"2024-07-02T23:00:03.716Z"},{"rank":159,"tracked_at":"2024-07-02T23:10:54.541Z"},{"rank":158,"tracked_at":"2024-07-02T23:12:30.070Z"},{"rank":157,"tracked_at":"2024-07-02T23:21:41.911Z"},{"rank":156,"tracked_at":"2024-07-02T23:23:18.503Z"},{"rank":155,"tracked_at":"2024-07-02T23:23:50.319Z"},{"rank":156,"tracked_at":"2024-07-02T23:24:25.436Z"},{"rank":155,"tracked_at":"2024-07-02T23:26:37.603Z"},{"rank":156,"tracked_at":"2024-07-02T23:28:46.040Z"},{"rank":157,"tracked_at":"2024-07-02T23:33:11.446Z"},{"rank":156,"tracked_at":"2024-07-02T23:33:43.096Z"},{"rank":157,"tracked_at":"2024-07-02T23:38:33.799Z"},{"rank":158,"tracked_at":"2024-07-02T23:40:42.894Z"},{"rank":159,"tracked_at":"2024-07-02T23:49:18.363Z"},{"rank":158,"tracked_at":"2024-07-02T23:50:53.986Z"},{"rank":157,"tracked_at":"2024-07-02T23:54:05.750Z"},{"rank":156,"tracked_at":"2024-07-02T23:55:42.894Z"},{"rank":157,"tracked_at":"2024-07-03T00:00:34.051Z"},{"rank":158,"tracked_at":"2024-07-03T00:03:14.177Z"},{"rank":157,"tracked_at":"2024-07-03T00:05:21.578Z"},{"rank":158,"tracked_at":"2024-07-03T00:09:07.101Z"},{"rank":159,"tracked_at":"2024-07-03T00:13:22.184Z"},{"rank":158,"tracked_at":"2024-07-03T00:17:02.057Z"},{"rank":159,"tracked_at":"2024-07-03T00:22:51.119Z"},{"rank":160,"tracked_at":"2024-07-03T00:23:54.368Z"},{"rank":161,"tracked_at":"2024-07-03T00:27:40.314Z"},{"rank":162,"tracked_at":"2024-07-03T00:35:05.313Z"},{"rank":163,"tracked_at":"2024-07-03T00:42:04.393Z"},{"rank":164,"tracked_at":"2024-07-03T00:43:39.920Z"},{"rank":166,"tracked_at":"2024-07-03T00:51:39.935Z"},{"rank":165,"tracked_at":"2024-07-03T00:53:47.251Z"},{"rank":164,"tracked_at":"2024-07-03T00:56:55.596Z"},{"rank":165,"tracked_at":"2024-07-03T01:00:40.292Z"},{"rank":164,"tracked_at":"2024-07-03T01:09:38.512Z"},{"rank":163,"tracked_at":"2024-07-03T01:14:22.951Z"},{"rank":162,"tracked_at":"2024-07-03T01:14:54.281Z"},{"rank":163,"tracked_at":"2024-07-03T01:15:59.141Z"},{"rank":162,"tracked_at":"2024-07-03T01:16:31.505Z"},{"rank":163,"tracked_at":"2024-07-03T01:23:54.532Z"},{"rank":164,"tracked_at":"2024-07-03T01:24:58.903Z"},{"rank":163,"tracked_at":"2024-07-03T01:32:26.096Z"},{"rank":164,"tracked_at":"2024-07-03T01:34:01.005Z"},{"rank":165,"tracked_at":"2024-07-03T01:35:38.331Z"},{"rank":166,"tracked_at":"2024-07-03T01:37:14.865Z"},{"rank":165,"tracked_at":"2024-07-03T01:38:18.016Z"},{"rank":166,"tracked_at":"2024-07-03T01:45:52.132Z"},{"rank":167,"tracked_at":"2024-07-03T02:03:20.701Z"},{"rank":168,"tracked_at":"2024-07-03T02:10:16.208Z"},{"rank":167,"tracked_at":"2024-07-03T02:11:20.035Z"},{"rank":168,"tracked_at":"2024-07-03T02:11:51.497Z"},{"rank":169,"tracked_at":"2024-07-03T02:12:54.773Z"},{"rank":170,"tracked_at":"2024-07-03T02:14:29.708Z"},{"rank":171,"tracked_at":"2024-07-03T02:21:55.303Z"},{"rank":170,"tracked_at":"2024-07-03T02:25:03.477Z"},{"rank":171,"tracked_at":"2024-07-03T02:26:37.950Z"},{"rank":170,"tracked_at":"2024-07-03T02:31:58.222Z"},{"rank":171,"tracked_at":"2024-07-03T02:34:36.667Z"},{"rank":170,"tracked_at":"2024-07-03T02:36:44.192Z"},{"rank":171,"tracked_at":"2024-07-03T02:39:23.530Z"},{"rank":170,"tracked_at":"2024-07-03T02:43:06.242Z"},{"rank":169,"tracked_at":"2024-07-03T02:43:38.012Z"},{"rank":170,"tracked_at":"2024-07-03T02:51:37.443Z"},{"rank":171,"tracked_at":"2024-07-03T02:52:08.675Z"},{"rank":170,"tracked_at":"2024-07-03T02:54:48.376Z"},{"rank":171,"tracked_at":"2024-07-03T02:56:55.797Z"},{"rank":172,"tracked_at":"2024-07-03T02:59:03.544Z"},{"rank":173,"tracked_at":"2024-07-03T03:01:10.386Z"},{"rank":174,"tracked_at":"2024-07-03T03:01:42.740Z"},{"rank":172,"tracked_at":"2024-07-03T03:02:45.758Z"},{"rank":173,"tracked_at":"2024-07-03T03:04:21.138Z"},{"rank":174,"tracked_at":"2024-07-03T03:06:25.899Z"},{"rank":173,"tracked_at":"2024-07-03T03:08:31.090Z"},{"rank":174,"tracked_at":"2024-07-03T03:25:54.312Z"},{"rank":175,"tracked_at":"2024-07-03T03:33:51.160Z"},{"rank":174,"tracked_at":"2024-07-03T03:34:54.680Z"},{"rank":173,"tracked_at":"2024-07-03T03:35:59.163Z"},{"rank":172,"tracked_at":"2024-07-03T03:39:43.808Z"},{"rank":173,"tracked_at":"2024-07-03T04:03:02.879Z"},{"rank":174,"tracked_at":"2024-07-03T04:04:38.291Z"},{"rank":175,"tracked_at":"2024-07-03T04:06:44.961Z"},{"rank":174,"tracked_at":"2024-07-03T04:13:02.946Z"},{"rank":175,"tracked_at":"2024-07-03T04:13:34.411Z"},{"rank":174,"tracked_at":"2024-07-03T04:16:12.173Z"},{"rank":175,"tracked_at":"2024-07-03T04:23:00.606Z"},{"rank":176,"tracked_at":"2024-07-03T04:27:46.522Z"},{"rank":177,"tracked_at":"2024-07-03T04:29:55.579Z"},{"rank":176,"tracked_at":"2024-07-03T04:35:13.752Z"},{"rank":175,"tracked_at":"2024-07-03T04:36:48.560Z"},{"rank":176,"tracked_at":"2024-07-03T04:52:47.434Z"},{"rank":177,"tracked_at":"2024-07-03T05:08:40.713Z"},{"rank":178,"tracked_at":"2024-07-03T05:20:16.612Z"},{"rank":177,"tracked_at":"2024-07-03T05:36:12.684Z"},{"rank":176,"tracked_at":"2024-07-03T05:48:21.119Z"},{"rank":177,"tracked_at":"2024-07-03T05:49:24.951Z"},{"rank":178,"tracked_at":"2024-07-03T05:51:35.816Z"},{"rank":179,"tracked_at":"2024-07-03T05:55:49.608Z"},{"rank":178,"tracked_at":"2024-07-03T06:12:48.360Z"},{"rank":177,"tracked_at":"2024-07-03T06:29:48.868Z"},{"rank":175,"tracked_at":"2024-07-03T06:33:34.348Z"},{"rank":176,"tracked_at":"2024-07-03T06:39:54.213Z"},{"rank":177,"tracked_at":"2024-07-03T06:56:17.902Z"},{"rank":178,"tracked_at":"2024-07-03T07:02:07.364Z"},{"rank":177,"tracked_at":"2024-07-03T07:12:12.272Z"},{"rank":178,"tracked_at":"2024-07-03T07:12:45.821Z"},{"rank":177,"tracked_at":"2024-07-03T07:26:01.462Z"},{"rank":176,"tracked_at":"2024-07-03T08:04:03.850Z"},{"rank":177,"tracked_at":"2024-07-03T08:14:42.532Z"},{"rank":176,"tracked_at":"2024-07-03T08:31:12.127Z"},{"rank":177,"tracked_at":"2024-07-03T08:48:19.253Z"},{"rank":176,"tracked_at":"2024-07-03T08:57:57.319Z"},{"rank":175,"tracked_at":"2024-07-03T09:00:35.641Z"},{"rank":174,"tracked_at":"2024-07-03T09:07:33.353Z"},{"rank":173,"tracked_at":"2024-07-03T09:08:05.344Z"},{"rank":171,"tracked_at":"2024-07-03T09:11:15.968Z"},{"rank":172,"tracked_at":"2024-07-03T09:14:26.204Z"},{"rank":173,"tracked_at":"2024-07-03T09:28:08.272Z"},{"rank":174,"tracked_at":"2024-07-03T09:56:50.357Z"},{"rank":173,"tracked_at":"2024-07-03T09:58:27.093Z"},{"rank":172,"tracked_at":"2024-07-03T10:05:21.672Z"},{"rank":173,"tracked_at":"2024-07-03T10:16:28.584Z"},{"rank":172,"tracked_at":"2024-07-03T10:19:07.873Z"},{"rank":173,"tracked_at":"2024-07-03T10:26:40.848Z"},{"rank":172,"tracked_at":"2024-07-03T10:35:45.375Z"},{"rank":173,"tracked_at":"2024-07-03T10:38:26.374Z"},{"rank":174,"tracked_at":"2024-07-03T10:39:59.787Z"},{"rank":173,"tracked_at":"2024-07-03T10:42:40.422Z"},{"rank":172,"tracked_at":"2024-07-03T10:58:32.455Z"},{"rank":173,"tracked_at":"2024-07-03T11:00:07.482Z"},{"rank":172,"tracked_at":"2024-07-03T11:15:40.377Z"},{"rank":171,"tracked_at":"2024-07-03T11:17:21.797Z"},{"rank":172,"tracked_at":"2024-07-03T11:18:26.541Z"},{"rank":171,"tracked_at":"2024-07-03T11:27:08.886Z"},{"rank":172,"tracked_at":"2024-07-03T11:29:15.774Z"},{"rank":173,"tracked_at":"2024-07-03T11:30:20.648Z"},{"rank":172,"tracked_at":"2024-07-03T11:38:20.627Z"},{"rank":175,"tracked_at":"2024-07-03T11:46:18.528Z"},{"rank":176,"tracked_at":"2024-07-03T11:48:59.274Z"},{"rank":177,"tracked_at":"2024-07-03T11:54:54.221Z"},{"rank":176,"tracked_at":"2024-07-03T12:06:46.286Z"},{"rank":175,"tracked_at":"2024-07-03T12:12:08.723Z"},{"rank":174,"tracked_at":"2024-07-03T12:16:59.293Z"},{"rank":175,"tracked_at":"2024-07-03T12:20:48.721Z"},{"rank":176,"tracked_at":"2024-07-03T12:24:33.267Z"},{"rank":177,"tracked_at":"2024-07-03T12:26:13.028Z"},{"rank":176,"tracked_at":"2024-07-03T12:26:44.602Z"},{"rank":175,"tracked_at":"2024-07-03T12:31:42.988Z"},{"rank":174,"tracked_at":"2024-07-03T12:32:15.036Z"},{"rank":173,"tracked_at":"2024-07-03T12:33:52.842Z"},{"rank":172,"tracked_at":"2024-07-03T12:38:39.553Z"},{"rank":173,"tracked_at":"2024-07-03T12:43:10.001Z"},{"rank":174,"tracked_at":"2024-07-03T12:44:52.018Z"},{"rank":173,"tracked_at":"2024-07-03T12:45:23.674Z"},{"rank":174,"tracked_at":"2024-07-03T12:51:26.619Z"},{"rank":175,"tracked_at":"2024-07-03T12:54:46.583Z"},{"rank":176,"tracked_at":"2024-07-03T12:55:19.766Z"},{"rank":177,"tracked_at":"2024-07-03T12:59:39.159Z"},{"rank":176,"tracked_at":"2024-07-03T13:00:10.451Z"},{"rank":177,"tracked_at":"2024-07-03T13:04:03.725Z"},{"rank":178,"tracked_at":"2024-07-03T13:04:36.173Z"},{"rank":179,"tracked_at":"2024-07-03T13:07:24.083Z"},{"rank":180,"tracked_at":"2024-07-03T13:10:37.650Z"},{"rank":179,"tracked_at":"2024-07-03T13:13:53.936Z"},{"rank":178,"tracked_at":"2024-07-03T13:16:40.054Z"},{"rank":179,"tracked_at":"2024-07-03T13:18:50.726Z"},{"rank":180,"tracked_at":"2024-07-03T13:22:34.449Z"},{"rank":181,"tracked_at":"2024-07-03T13:31:18.259Z"},{"rank":180,"tracked_at":"2024-07-03T13:31:50.235Z"},{"rank":179,"tracked_at":"2024-07-03T13:37:49.193Z"},{"rank":180,"tracked_at":"2024-07-03T13:51:28.459Z"},{"rank":179,"tracked_at":"2024-07-03T13:52:00.723Z"},{"rank":178,"tracked_at":"2024-07-03T13:56:22.084Z"},{"rank":177,"tracked_at":"2024-07-03T14:01:50.717Z"},{"rank":178,"tracked_at":"2024-07-03T14:13:28.643Z"},{"rank":179,"tracked_at":"2024-07-03T14:16:13.080Z"},{"rank":180,"tracked_at":"2024-07-03T14:17:17.043Z"},{"rank":181,"tracked_at":"2024-07-03T14:18:52.665Z"},{"rank":182,"tracked_at":"2024-07-03T14:19:26.162Z"},{"rank":181,"tracked_at":"2024-07-03T14:21:39.536Z"},{"rank":182,"tracked_at":"2024-07-03T14:24:35.048Z"},{"rank":183,"tracked_at":"2024-07-03T14:25:06.986Z"},{"rank":184,"tracked_at":"2024-07-03T14:26:18.985Z"},{"rank":183,"tracked_at":"2024-07-03T14:27:23.803Z"},{"rank":182,"tracked_at":"2024-07-03T14:27:57.208Z"},{"rank":183,"tracked_at":"2024-07-03T14:31:46.400Z"},{"rank":185,"tracked_at":"2024-07-03T14:32:19.764Z"},{"rank":186,"tracked_at":"2024-07-03T14:33:27.714Z"},{"rank":185,"tracked_at":"2024-07-03T14:34:34.726Z"},{"rank":186,"tracked_at":"2024-07-03T14:37:20.355Z"},{"rank":187,"tracked_at":"2024-07-03T14:38:26.381Z"},{"rank":189,"tracked_at":"2024-07-03T14:41:42.687Z"},{"rank":188,"tracked_at":"2024-07-03T14:43:22.432Z"},{"rank":187,"tracked_at":"2024-07-03T14:50:41.622Z"},{"rank":188,"tracked_at":"2024-07-03T14:53:59.822Z"},{"rank":187,"tracked_at":"2024-07-03T14:54:33.026Z"},{"rank":188,"tracked_at":"2024-07-03T14:56:43.429Z"},{"rank":187,"tracked_at":"2024-07-03T14:59:28.127Z"},{"rank":188,"tracked_at":"2024-07-03T15:02:20.725Z"},{"rank":187,"tracked_at":"2024-07-03T15:05:05.868Z"},{"rank":185,"tracked_at":"2024-07-03T15:05:39.374Z"},{"rank":186,"tracked_at":"2024-07-03T15:07:19.984Z"},{"rank":185,"tracked_at":"2024-07-03T15:07:52.991Z"},{"rank":187,"tracked_at":"2024-07-03T15:16:05.405Z"},{"rank":188,"tracked_at":"2024-07-03T15:17:10.303Z"},{"rank":189,"tracked_at":"2024-07-03T15:21:04.991Z"},{"rank":190,"tracked_at":"2024-07-03T15:24:24.212Z"},{"rank":189,"tracked_at":"2024-07-03T15:29:16.262Z"},{"rank":188,"tracked_at":"2024-07-03T15:30:55.681Z"},{"rank":187,"tracked_at":"2024-07-03T15:31:28.513Z"},{"rank":186,"tracked_at":"2024-07-03T15:35:29.077Z"},{"rank":185,"tracked_at":"2024-07-03T15:45:33.361Z"},{"rank":184,"tracked_at":"2024-07-03T15:49:59.343Z"},{"rank":183,"tracked_at":"2024-07-03T15:56:07.138Z"},{"rank":184,"tracked_at":"2024-07-03T16:06:05.428Z"},{"rank":185,"tracked_at":"2024-07-03T16:06:37.737Z"},{"rank":184,"tracked_at":"2024-07-03T16:12:46.348Z"},{"rank":185,"tracked_at":"2024-07-03T16:13:18.770Z"},{"rank":187,"tracked_at":"2024-07-03T16:13:54.040Z"},{"rank":188,"tracked_at":"2024-07-03T16:16:07.899Z"},{"rank":187,"tracked_at":"2024-07-03T16:21:07.851Z"},{"rank":188,"tracked_at":"2024-07-03T16:23:19.143Z"},{"rank":189,"tracked_at":"2024-07-03T16:23:52.885Z"},{"rank":190,"tracked_at":"2024-07-03T16:27:15.551Z"},{"rank":191,"tracked_at":"2024-07-03T16:29:22.602Z"},{"rank":190,"tracked_at":"2024-07-03T16:30:28.757Z"},{"rank":191,"tracked_at":"2024-07-03T16:31:34.791Z"},{"rank":192,"tracked_at":"2024-07-03T16:32:08.071Z"},{"rank":191,"tracked_at":"2024-07-03T16:33:50.067Z"},{"rank":192,"tracked_at":"2024-07-03T16:34:58.643Z"},{"rank":193,"tracked_at":"2024-07-03T16:36:39.810Z"},{"rank":194,"tracked_at":"2024-07-03T16:39:29.112Z"},{"rank":195,"tracked_at":"2024-07-03T16:40:34.456Z"},{"rank":194,"tracked_at":"2024-07-03T16:43:21.287Z"},{"rank":193,"tracked_at":"2024-07-03T16:45:04.300Z"},{"rank":194,"tracked_at":"2024-07-03T16:46:45.994Z"},{"rank":195,"tracked_at":"2024-07-03T16:48:58.720Z"},{"rank":196,"tracked_at":"2024-07-03T16:54:27.287Z"},{"rank":197,"tracked_at":"2024-07-03T17:04:44.419Z"},{"rank":198,"tracked_at":"2024-07-03T17:05:49.619Z"},{"rank":199,"tracked_at":"2024-07-03T17:07:28.008Z"},{"rank":200,"tracked_at":"2024-07-03T17:10:09.905Z"},{"rank":199,"tracked_at":"2024-07-03T17:12:52.755Z"},{"rank":198,"tracked_at":"2024-07-03T17:14:30.810Z"},{"rank":197,"tracked_at":"2024-07-03T17:15:03.616Z"},{"rank":198,"tracked_at":"2024-07-03T17:15:35.913Z"},{"rank":199,"tracked_at":"2024-07-03T17:17:44.995Z"},{"rank":200,"tracked_at":"2024-07-03T17:21:01.992Z"},{"rank":199,"tracked_at":"2024-07-03T17:22:11.833Z"},{"rank":200,"tracked_at":"2024-07-03T17:22:44.916Z"},{"rank":201,"tracked_at":"2024-07-03T17:23:52.570Z"},{"rank":200,"tracked_at":"2024-07-03T17:31:27.783Z"},{"rank":199,"tracked_at":"2024-07-03T17:33:39.433Z"},{"rank":200,"tracked_at":"2024-07-03T17:34:45.590Z"},{"rank":201,"tracked_at":"2024-07-03T17:37:02.534Z"},{"rank":202,"tracked_at":"2024-07-03T17:37:35.074Z"},{"rank":203,"tracked_at":"2024-07-03T17:40:55.188Z"},{"rank":205,"tracked_at":"2024-07-03T17:42:33.428Z"},{"rank":206,"tracked_at":"2024-07-03T17:43:06.576Z"},{"rank":207,"tracked_at":"2024-07-03T17:44:49.211Z"},{"rank":208,"tracked_at":"2024-07-03T17:45:58.301Z"},{"rank":209,"tracked_at":"2024-07-03T17:54:23.385Z"},{"rank":210,"tracked_at":"2024-07-03T18:06:35.536Z"},{"rank":212,"tracked_at":"2024-07-03T18:13:42.784Z"},{"rank":211,"tracked_at":"2024-07-03T18:16:56.590Z"},{"rank":212,"tracked_at":"2024-07-03T18:23:26.063Z"},{"rank":211,"tracked_at":"2024-07-03T18:25:04.520Z"},{"rank":210,"tracked_at":"2024-07-03T18:25:36.902Z"},{"rank":209,"tracked_at":"2024-07-03T18:28:16.494Z"},{"rank":208,"tracked_at":"2024-07-03T18:29:55.954Z"},{"rank":209,"tracked_at":"2024-07-03T18:30:27.758Z"},{"rank":211,"tracked_at":"2024-07-03T18:32:08.470Z"},{"rank":210,"tracked_at":"2024-07-03T18:33:16.592Z"},{"rank":208,"tracked_at":"2024-07-03T18:36:01.642Z"},{"rank":207,"tracked_at":"2024-07-03T18:36:33.783Z"},{"rank":208,"tracked_at":"2024-07-03T18:37:06.050Z"},{"rank":209,"tracked_at":"2024-07-03T18:53:48.939Z"},{"rank":208,"tracked_at":"2024-07-03T18:58:39.314Z"},{"rank":207,"tracked_at":"2024-07-03T18:59:46.273Z"},{"rank":206,"tracked_at":"2024-07-03T19:01:23.141Z"},{"rank":207,"tracked_at":"2024-07-03T19:02:31.927Z"},{"rank":208,"tracked_at":"2024-07-03T19:03:06.911Z"},{"rank":207,"tracked_at":"2024-07-03T19:04:45.873Z"},{"rank":208,"tracked_at":"2024-07-03T19:09:05.611Z"},{"rank":209,"tracked_at":"2024-07-03T19:15:35.493Z"},{"rank":210,"tracked_at":"2024-07-03T19:22:43.241Z"},{"rank":209,"tracked_at":"2024-07-03T19:23:18.157Z"},{"rank":210,"tracked_at":"2024-07-03T19:26:33.646Z"},{"rank":209,"tracked_at":"2024-07-03T19:28:42.356Z"},{"rank":210,"tracked_at":"2024-07-03T19:30:51.399Z"},{"rank":211,"tracked_at":"2024-07-03T19:33:00.966Z"},{"rank":210,"tracked_at":"2024-07-03T19:35:44.763Z"},{"rank":211,"tracked_at":"2024-07-03T19:37:55.517Z"},{"rank":210,"tracked_at":"2024-07-03T19:46:06.042Z"},{"rank":209,"tracked_at":"2024-07-03T19:47:11.395Z"},{"rank":210,"tracked_at":"2024-07-03T19:54:11.819Z"},{"rank":209,"tracked_at":"2024-07-03T19:54:48.497Z"},{"rank":210,"tracked_at":"2024-07-03T19:55:20.861Z"},{"rank":209,"tracked_at":"2024-07-03T19:59:35.464Z"},{"rank":210,"tracked_at":"2024-07-03T20:04:00.626Z"},{"rank":211,"tracked_at":"2024-07-03T20:04:32.694Z"},{"rank":213,"tracked_at":"2024-07-03T20:05:38.286Z"},{"rank":211,"tracked_at":"2024-07-03T20:12:40.987Z"},{"rank":210,"tracked_at":"2024-07-03T20:18:37.370Z"},{"rank":211,"tracked_at":"2024-07-03T20:20:14.889Z"},{"rank":210,"tracked_at":"2024-07-03T20:26:47.749Z"},{"rank":211,"tracked_at":"2024-07-03T20:30:32.977Z"},{"rank":212,"tracked_at":"2024-07-03T20:32:44.800Z"},{"rank":211,"tracked_at":"2024-07-03T20:33:49.534Z"},{"rank":212,"tracked_at":"2024-07-03T20:34:53.967Z"},{"rank":211,"tracked_at":"2024-07-03T20:37:03.321Z"},{"rank":212,"tracked_at":"2024-07-03T20:37:36.490Z"},{"rank":211,"tracked_at":"2024-07-03T20:38:40.825Z"},{"rank":212,"tracked_at":"2024-07-03T20:41:26.188Z"},{"rank":211,"tracked_at":"2024-07-03T20:42:01.563Z"},{"rank":212,"tracked_at":"2024-07-03T20:48:40.821Z"},{"rank":211,"tracked_at":"2024-07-03T20:51:26.041Z"},{"rank":212,"tracked_at":"2024-07-03T20:53:41.632Z"},{"rank":211,"tracked_at":"2024-07-03T20:54:15.735Z"},{"rank":212,"tracked_at":"2024-07-03T20:59:20.042Z"},{"rank":213,"tracked_at":"2024-07-03T20:59:52.531Z"},{"rank":214,"tracked_at":"2024-07-03T21:02:13.465Z"},{"rank":215,"tracked_at":"2024-07-03T21:03:21.965Z"},{"rank":216,"tracked_at":"2024-07-03T21:04:29.011Z"},{"rank":215,"tracked_at":"2024-07-03T21:14:57.359Z"},{"rank":214,"tracked_at":"2024-07-03T21:15:28.925Z"},{"rank":213,"tracked_at":"2024-07-03T21:16:02.035Z"},{"rank":212,"tracked_at":"2024-07-03T21:18:45.642Z"},{"rank":211,"tracked_at":"2024-07-03T21:23:03.908Z"},{"rank":212,"tracked_at":"2024-07-03T21:25:11.806Z"},{"rank":211,"tracked_at":"2024-07-03T21:27:19.978Z"},{"rank":212,"tracked_at":"2024-07-03T21:27:52.996Z"},{"rank":213,"tracked_at":"2024-07-03T21:29:30.251Z"},{"rank":214,"tracked_at":"2024-07-03T21:32:54.120Z"},{"rank":213,"tracked_at":"2024-07-03T21:34:30.933Z"},{"rank":212,"tracked_at":"2024-07-03T21:41:06.034Z"},{"rank":213,"tracked_at":"2024-07-03T21:47:37.722Z"},{"rank":212,"tracked_at":"2024-07-03T21:53:33.639Z"},{"rank":213,"tracked_at":"2024-07-03T21:56:48.418Z"},{"rank":215,"tracked_at":"2024-07-03T21:57:56.154Z"},{"rank":216,"tracked_at":"2024-07-03T21:58:27.924Z"},{"rank":219,"tracked_at":"2024-07-03T21:58:59.583Z"},{"rank":220,"tracked_at":"2024-07-03T22:00:06.512Z"},{"rank":219,"tracked_at":"2024-07-03T22:02:17.111Z"},{"rank":220,"tracked_at":"2024-07-03T22:02:48.892Z"},{"rank":224,"tracked_at":"2024-07-03T22:05:01.854Z"},{"rank":223,"tracked_at":"2024-07-03T22:05:36.656Z"},{"rank":224,"tracked_at":"2024-07-03T22:07:13.356Z"},{"rank":225,"tracked_at":"2024-07-03T22:07:46.132Z"},{"rank":226,"tracked_at":"2024-07-03T22:08:21.957Z"},{"rank":227,"tracked_at":"2024-07-03T22:11:08.724Z"},{"rank":228,"tracked_at":"2024-07-03T22:12:51.644Z"},{"rank":229,"tracked_at":"2024-07-03T22:13:24.815Z"},{"rank":230,"tracked_at":"2024-07-03T22:15:35.324Z"},{"rank":229,"tracked_at":"2024-07-03T22:16:07.525Z"},{"rank":230,"tracked_at":"2024-07-03T22:18:22.984Z"},{"rank":232,"tracked_at":"2024-07-03T22:18:55.631Z"},{"rank":231,"tracked_at":"2024-07-03T22:19:28.181Z"},{"rank":232,"tracked_at":"2024-07-03T22:20:32.366Z"},{"rank":231,"tracked_at":"2024-07-03T22:21:05.296Z"},{"rank":232,"tracked_at":"2024-07-03T22:22:12.382Z"},{"rank":233,"tracked_at":"2024-07-03T22:24:59.243Z"},{"rank":232,"tracked_at":"2024-07-03T22:25:30.998Z"},{"rank":233,"tracked_at":"2024-07-03T22:26:36.940Z"},{"rank":234,"tracked_at":"2024-07-03T22:28:52.255Z"},{"rank":233,"tracked_at":"2024-07-03T22:31:40.982Z"},{"rank":232,"tracked_at":"2024-07-03T22:32:47.789Z"},{"rank":233,"tracked_at":"2024-07-03T22:33:54.664Z"},{"rank":234,"tracked_at":"2024-07-03T22:34:27.093Z"},{"rank":233,"tracked_at":"2024-07-03T22:36:06.198Z"},{"rank":234,"tracked_at":"2024-07-03T22:37:13.950Z"},{"rank":233,"tracked_at":"2024-07-03T22:38:20.108Z"},{"rank":232,"tracked_at":"2024-07-03T22:46:06.580Z"},{"rank":233,"tracked_at":"2024-07-03T22:47:44.812Z"},{"rank":234,"tracked_at":"2024-07-03T22:51:04.029Z"},{"rank":235,"tracked_at":"2024-07-03T22:51:36.983Z"},{"rank":234,"tracked_at":"2024-07-03T22:58:52.691Z"},{"rank":235,"tracked_at":"2024-07-03T23:01:03.703Z"},{"rank":236,"tracked_at":"2024-07-03T23:02:42.720Z"},{"rank":235,"tracked_at":"2024-07-03T23:04:22.088Z"},{"rank":234,"tracked_at":"2024-07-03T23:05:30.131Z"},{"rank":233,"tracked_at":"2024-07-03T23:08:45.408Z"},{"rank":234,"tracked_at":"2024-07-03T23:20:51.954Z"},{"rank":233,"tracked_at":"2024-07-03T23:26:20.800Z"},{"rank":234,"tracked_at":"2024-07-03T23:26:54.921Z"},{"rank":235,"tracked_at":"2024-07-03T23:27:58.967Z"},{"rank":236,"tracked_at":"2024-07-03T23:30:17.418Z"},{"rank":237,"tracked_at":"2024-07-03T23:31:23.216Z"},{"rank":238,"tracked_at":"2024-07-03T23:32:58.185Z"},{"rank":239,"tracked_at":"2024-07-03T23:34:01.494Z"},{"rank":240,"tracked_at":"2024-07-03T23:35:06.123Z"},{"rank":241,"tracked_at":"2024-07-03T23:36:45.159Z"},{"rank":240,"tracked_at":"2024-07-03T23:45:20.947Z"},{"rank":241,"tracked_at":"2024-07-03T23:45:56.109Z"},{"rank":240,"tracked_at":"2024-07-03T23:49:44.267Z"},{"rank":241,"tracked_at":"2024-07-03T23:56:08.189Z"},{"rank":239,"tracked_at":"2024-07-03T23:58:49.121Z"},{"rank":238,"tracked_at":"2024-07-03T23:59:54.100Z"},{"rank":239,"tracked_at":"2024-07-04T00:07:02.278Z"},{"rank":240,"tracked_at":"2024-07-04T00:09:41.193Z"},{"rank":241,"tracked_at":"2024-07-04T00:12:29.023Z"},{"rank":242,"tracked_at":"2024-07-04T00:13:00.630Z"},{"rank":243,"tracked_at":"2024-07-04T00:21:34.702Z"},{"rank":244,"tracked_at":"2024-07-04T00:33:51.408Z"},{"rank":245,"tracked_at":"2024-07-04T00:36:32.105Z"},{"rank":246,"tracked_at":"2024-07-04T00:38:37.836Z"},{"rank":247,"tracked_at":"2024-07-04T00:41:16.126Z"},{"rank":248,"tracked_at":"2024-07-04T00:51:54.797Z"},{"rank":249,"tracked_at":"2024-07-04T00:54:34.545Z"},{"rank":248,"tracked_at":"2024-07-04T01:07:28.557Z"},{"rank":249,"tracked_at":"2024-07-04T01:07:59.737Z"},{"rank":248,"tracked_at":"2024-07-04T01:16:42.382Z"},{"rank":247,"tracked_at":"2024-07-04T01:20:25.905Z"},{"rank":248,"tracked_at":"2024-07-04T01:22:04.451Z"},{"rank":247,"tracked_at":"2024-07-04T01:42:18.783Z"},{"rank":248,"tracked_at":"2024-07-04T01:48:44.916Z"},{"rank":247,"tracked_at":"2024-07-04T01:51:26.659Z"},{"rank":248,"tracked_at":"2024-07-04T01:58:49.339Z"},{"rank":249,"tracked_at":"2024-07-04T02:16:32.386Z"},{"rank":250,"tracked_at":"2024-07-04T02:28:39.626Z"},{"rank":249,"tracked_at":"2024-07-04T02:34:32.928Z"},{"rank":250,"tracked_at":"2024-07-04T02:40:28.331Z"},{"rank":251,"tracked_at":"2024-07-04T03:00:43.605Z"},{"rank":240,"tracked_at":"2024-07-04T03:02:07.261Z"},{"rank":241,"tracked_at":"2024-07-04T03:03:42.781Z"},{"rank":240,"tracked_at":"2024-07-04T03:06:49.445Z"},{"rank":239,"tracked_at":"2024-07-04T03:12:38.430Z"},{"rank":240,"tracked_at":"2024-07-04T03:18:30.446Z"},{"rank":239,"tracked_at":"2024-07-04T03:20:08.114Z"},{"rank":240,"tracked_at":"2024-07-04T03:20:39.508Z"},{"rank":241,"tracked_at":"2024-07-04T03:23:50.828Z"},{"rank":242,"tracked_at":"2024-07-04T03:24:55.252Z"},{"rank":243,"tracked_at":"2024-07-04T03:25:26.401Z"},{"rank":244,"tracked_at":"2024-07-04T03:27:00.603Z"},{"rank":243,"tracked_at":"2024-07-04T03:27:32.095Z"},{"rank":244,"tracked_at":"2024-07-04T03:28:34.105Z"},{"rank":245,"tracked_at":"2024-07-04T03:29:36.102Z"},{"rank":246,"tracked_at":"2024-07-04T03:31:11.992Z"},{"rank":247,"tracked_at":"2024-07-04T03:31:43.455Z"},{"rank":248,"tracked_at":"2024-07-04T03:32:14.580Z"},{"rank":247,"tracked_at":"2024-07-04T03:33:50.651Z"},{"rank":246,"tracked_at":"2024-07-04T03:38:00.573Z"},{"rank":245,"tracked_at":"2024-07-04T03:40:07.412Z"},{"rank":246,"tracked_at":"2024-07-04T03:40:39.512Z"},{"rank":245,"tracked_at":"2024-07-04T03:52:15.030Z"},{"rank":246,"tracked_at":"2024-07-04T03:52:47.010Z"},{"rank":248,"tracked_at":"2024-07-04T03:55:25.679Z"},{"rank":247,"tracked_at":"2024-07-04T03:56:29.750Z"},{"rank":246,"tracked_at":"2024-07-04T03:58:37.052Z"},{"rank":247,"tracked_at":"2024-07-04T04:06:08.253Z"},{"rank":246,"tracked_at":"2024-07-04T04:15:43.635Z"},{"rank":247,"tracked_at":"2024-07-04T04:30:36.388Z"},{"rank":246,"tracked_at":"2024-07-04T04:32:42.291Z"},{"rank":247,"tracked_at":"2024-07-04T04:40:03.414Z"},{"rank":246,"tracked_at":"2024-07-04T04:41:40.111Z"},{"rank":245,"tracked_at":"2024-07-04T04:44:20.621Z"},{"rank":244,"tracked_at":"2024-07-04T04:45:58.146Z"},{"rank":245,"tracked_at":"2024-07-04T04:55:24.709Z"},{"rank":248,"tracked_at":"2024-07-04T04:56:27.132Z"},{"rank":249,"tracked_at":"2024-07-04T04:56:59.818Z"},{"rank":250,"tracked_at":"2024-07-04T04:57:31.212Z"},{"rank":251,"tracked_at":"2024-07-04T05:00:11.742Z"},{"rank":249,"tracked_at":"2024-07-04T05:04:56.827Z"},{"rank":250,"tracked_at":"2024-07-04T05:08:07.339Z"},{"rank":249,"tracked_at":"2024-07-04T05:11:16.430Z"},{"rank":250,"tracked_at":"2024-07-04T05:15:59.570Z"},{"rank":249,"tracked_at":"2024-07-04T05:16:30.705Z"},{"rank":248,"tracked_at":"2024-07-04T05:17:02.050Z"},{"rank":247,"tracked_at":"2024-07-04T05:25:28.989Z"},{"rank":246,"tracked_at":"2024-07-04T05:30:44.129Z"},{"rank":245,"tracked_at":"2024-07-04T05:31:16.475Z"},{"rank":246,"tracked_at":"2024-07-04T05:32:19.740Z"},{"rank":247,"tracked_at":"2024-07-04T05:44:28.411Z"},{"rank":248,"tracked_at":"2024-07-04T05:45:32.475Z"},{"rank":247,"tracked_at":"2024-07-04T05:51:20.650Z"},{"rank":246,"tracked_at":"2024-07-04T05:57:49.537Z"},{"rank":248,"tracked_at":"2024-07-04T06:10:02.517Z"},{"rank":249,"tracked_at":"2024-07-04T06:23:48.525Z"},{"rank":248,"tracked_at":"2024-07-04T06:24:53.496Z"},{"rank":247,"tracked_at":"2024-07-04T06:28:03.299Z"},{"rank":246,"tracked_at":"2024-07-04T06:30:40.494Z"},{"rank":244,"tracked_at":"2024-07-04T06:34:20.793Z"},{"rank":245,"tracked_at":"2024-07-04T06:35:57.852Z"},{"rank":244,"tracked_at":"2024-07-04T06:51:24.455Z"},{"rank":243,"tracked_at":"2024-07-04T06:52:57.608Z"},{"rank":244,"tracked_at":"2024-07-04T06:58:45.115Z"},{"rank":243,"tracked_at":"2024-07-04T07:01:24.266Z"},{"rank":242,"tracked_at":"2024-07-04T07:05:41.006Z"},{"rank":243,"tracked_at":"2024-07-04T07:09:53.470Z"},{"rank":242,"tracked_at":"2024-07-04T07:37:21.990Z"},{"rank":243,"tracked_at":"2024-07-04T07:41:35.821Z"},{"rank":244,"tracked_at":"2024-07-04T07:42:08.785Z"},{"rank":245,"tracked_at":"2024-07-04T07:45:51.448Z"},{"rank":244,"tracked_at":"2024-07-04T07:53:15.255Z"},{"rank":245,"tracked_at":"2024-07-04T07:54:50.635Z"},{"rank":244,"tracked_at":"2024-07-04T07:55:21.919Z"},{"rank":243,"tracked_at":"2024-07-04T07:57:59.586Z"},{"rank":242,"tracked_at":"2024-07-04T08:03:17.884Z"},{"rank":243,"tracked_at":"2024-07-04T08:07:01.490Z"},{"rank":244,"tracked_at":"2024-07-04T08:08:36.483Z"},{"rank":243,"tracked_at":"2024-07-04T08:11:15.162Z"},{"rank":244,"tracked_at":"2024-07-04T08:11:46.464Z"},{"rank":243,"tracked_at":"2024-07-04T08:23:21.462Z"},{"rank":245,"tracked_at":"2024-07-04T08:28:34.595Z"},{"rank":246,"tracked_at":"2024-07-04T08:29:06.307Z"},{"rank":247,"tracked_at":"2024-07-04T08:29:37.822Z"},{"rank":248,"tracked_at":"2024-07-04T08:31:14.660Z"},{"rank":249,"tracked_at":"2024-07-04T08:35:28.124Z"},{"rank":250,"tracked_at":"2024-07-04T08:39:42.964Z"},{"rank":249,"tracked_at":"2024-07-04T08:43:24.801Z"},{"rank":248,"tracked_at":"2024-07-04T08:43:56.109Z"},{"rank":247,"tracked_at":"2024-07-04T08:58:43.133Z"},{"rank":246,"tracked_at":"2024-07-04T08:59:46.311Z"},{"rank":247,"tracked_at":"2024-07-04T09:08:41.930Z"},{"rank":246,"tracked_at":"2024-07-04T09:11:19.382Z"},{"rank":245,"tracked_at":"2024-07-04T09:12:53.366Z"},{"rank":246,"tracked_at":"2024-07-04T09:15:02.177Z"},{"rank":247,"tracked_at":"2024-07-04T09:21:54.140Z"},{"rank":248,"tracked_at":"2024-07-04T09:26:12.027Z"},{"rank":247,"tracked_at":"2024-07-04T09:27:15.129Z"},{"rank":246,"tracked_at":"2024-07-04T09:31:57.463Z"},{"rank":247,"tracked_at":"2024-07-04T09:34:34.802Z"},{"rank":246,"tracked_at":"2024-07-04T09:35:38.211Z"},{"rank":245,"tracked_at":"2024-07-04T09:37:44.720Z"},{"rank":244,"tracked_at":"2024-07-04T09:44:37.382Z"},{"rank":245,"tracked_at":"2024-07-04T09:59:20.921Z"},{"rank":246,"tracked_at":"2024-07-04T10:00:22.972Z"},{"rank":245,"tracked_at":"2024-07-04T10:04:02.311Z"},{"rank":246,"tracked_at":"2024-07-04T10:16:10.589Z"},{"rank":248,"tracked_at":"2024-07-04T10:32:55.078Z"},{"rank":247,"tracked_at":"2024-07-04T10:33:25.973Z"},{"rank":248,"tracked_at":"2024-07-04T10:42:22.819Z"},{"rank":249,"tracked_at":"2024-07-04T10:50:17.063Z"},{"rank":248,"tracked_at":"2024-07-04T10:51:53.464Z"},{"rank":247,"tracked_at":"2024-07-04T10:52:56.259Z"},{"rank":246,"tracked_at":"2024-07-04T10:59:46.811Z"},{"rank":247,"tracked_at":"2024-07-04T11:06:04.962Z"},{"rank":248,"tracked_at":"2024-07-04T11:10:18.254Z"},{"rank":249,"tracked_at":"2024-07-04T11:17:46.417Z"},{"rank":250,"tracked_at":"2024-07-04T11:21:28.818Z"},{"rank":251,"tracked_at":"2024-07-04T11:26:16.311Z"},{"rank":252,"tracked_at":"2024-07-04T11:26:48.615Z"},{"rank":253,"tracked_at":"2024-07-04T11:27:20.600Z"},{"rank":255,"tracked_at":"2024-07-04T11:27:51.767Z"},{"rank":254,"tracked_at":"2024-07-04T11:37:48.382Z"},{"rank":253,"tracked_at":"2024-07-04T11:38:19.974Z"},{"rank":254,"tracked_at":"2024-07-04T11:55:50.445Z"},{"rank":255,"tracked_at":"2024-07-04T12:01:06.910Z"},{"rank":254,"tracked_at":"2024-07-04T12:09:04.640Z"},{"rank":255,"tracked_at":"2024-07-04T12:19:45.357Z"},{"rank":256,"tracked_at":"2024-07-04T12:30:57.515Z"},{"rank":257,"tracked_at":"2024-07-04T12:43:18.449Z"},{"rank":258,"tracked_at":"2024-07-04T12:44:24.144Z"},{"rank":259,"tracked_at":"2024-07-04T12:50:19.535Z"},{"rank":260,"tracked_at":"2024-07-04T12:53:01.880Z"},{"rank":259,"tracked_at":"2024-07-04T13:02:15.775Z"},{"rank":260,"tracked_at":"2024-07-04T13:06:06.186Z"},{"rank":261,"tracked_at":"2024-07-04T13:08:19.022Z"},{"rank":262,"tracked_at":"2024-07-04T13:08:51.031Z"},{"rank":263,"tracked_at":"2024-07-04T13:13:13.688Z"},{"rank":264,"tracked_at":"2024-07-04T13:15:53.559Z"},{"rank":265,"tracked_at":"2024-07-04T13:21:09.949Z"},{"rank":264,"tracked_at":"2024-07-04T13:23:49.679Z"},{"rank":263,"tracked_at":"2024-07-04T13:28:44.488Z"},{"rank":264,"tracked_at":"2024-07-04T13:37:52.104Z"},{"rank":263,"tracked_at":"2024-07-04T13:39:01.046Z"},{"rank":262,"tracked_at":"2024-07-04T13:42:13.206Z"},{"rank":264,"tracked_at":"2024-07-04T13:44:26.192Z"},{"rank":263,"tracked_at":"2024-07-04T13:45:01.032Z"},{"rank":262,"tracked_at":"2024-07-04T13:48:17.229Z"},{"rank":261,"tracked_at":"2024-07-04T13:52:01.739Z"},{"rank":262,"tracked_at":"2024-07-04T13:53:06.893Z"},{"rank":261,"tracked_at":"2024-07-04T13:55:47.479Z"},{"rank":260,"tracked_at":"2024-07-04T13:56:54.406Z"},{"rank":259,"tracked_at":"2024-07-04T13:58:33.094Z"},{"rank":258,"tracked_at":"2024-07-04T14:04:29.697Z"},{"rank":257,"tracked_at":"2024-07-04T14:12:32.194Z"},{"rank":256,"tracked_at":"2024-07-04T14:13:35.481Z"},{"rank":255,"tracked_at":"2024-07-04T14:24:57.050Z"},{"rank":256,"tracked_at":"2024-07-04T14:29:47.363Z"},{"rank":257,"tracked_at":"2024-07-04T14:30:53.724Z"},{"rank":256,"tracked_at":"2024-07-04T14:36:44.737Z"},{"rank":255,"tracked_at":"2024-07-04T14:37:49.497Z"},{"rank":256,"tracked_at":"2024-07-04T14:42:41.218Z"},{"rank":255,"tracked_at":"2024-07-04T14:55:05.595Z"},{"rank":254,"tracked_at":"2024-07-04T14:57:14.745Z"},{"rank":253,"tracked_at":"2024-07-04T14:58:51.539Z"},{"rank":252,"tracked_at":"2024-07-04T14:59:23.807Z"},{"rank":251,"tracked_at":"2024-07-04T15:09:16.638Z"},{"rank":250,"tracked_at":"2024-07-04T15:10:20.568Z"},{"rank":249,"tracked_at":"2024-07-04T15:10:53.658Z"},{"rank":250,"tracked_at":"2024-07-04T15:11:58.190Z"},{"rank":249,"tracked_at":"2024-07-04T15:12:30.975Z"},{"rank":248,"tracked_at":"2024-07-04T15:16:16.836Z"},{"rank":247,"tracked_at":"2024-07-04T15:20:09.181Z"},{"rank":248,"tracked_at":"2024-07-04T15:26:01.919Z"},{"rank":249,"tracked_at":"2024-07-04T15:41:09.635Z"},{"rank":250,"tracked_at":"2024-07-04T15:43:20.414Z"},{"rank":249,"tracked_at":"2024-07-04T15:47:34.562Z"},{"rank":251,"tracked_at":"2024-07-04T15:51:20.410Z"},{"rank":250,"tracked_at":"2024-07-04T16:03:45.565Z"},{"rank":251,"tracked_at":"2024-07-04T16:07:32.924Z"},{"rank":252,"tracked_at":"2024-07-04T16:09:44.582Z"},{"rank":253,"tracked_at":"2024-07-04T16:16:15.503Z"},{"rank":255,"tracked_at":"2024-07-04T16:26:10.346Z"},{"rank":256,"tracked_at":"2024-07-04T16:26:41.637Z"},{"rank":255,"tracked_at":"2024-07-04T16:34:49.326Z"},{"rank":254,"tracked_at":"2024-07-04T16:46:48.862Z"},{"rank":256,"tracked_at":"2024-07-04T16:47:20.415Z"},{"rank":255,"tracked_at":"2024-07-04T16:50:34.027Z"},{"rank":254,"tracked_at":"2024-07-04T17:04:48.102Z"},{"rank":255,"tracked_at":"2024-07-04T17:09:05.227Z"},{"rank":254,"tracked_at":"2024-07-04T17:09:38.013Z"},{"rank":255,"tracked_at":"2024-07-04T17:19:22.126Z"},{"rank":256,"tracked_at":"2024-07-04T17:19:53.943Z"},{"rank":257,"tracked_at":"2024-07-04T17:21:36.761Z"},{"rank":258,"tracked_at":"2024-07-04T17:23:18.732Z"},{"rank":259,"tracked_at":"2024-07-04T17:26:05.065Z"},{"rank":260,"tracked_at":"2024-07-04T17:40:00.984Z"}]}